{
"meta":{"test_sets":[],"test_metrics":[],"learn_metrics":[{"best_value":"Min","name":"RMSE"}],"launch_mode":"Train","parameters":"","iteration_count":1000,"learn_sets":["learn"],"name":"experiment"},
"iterations":[
{"learn":[14.61268541],"iteration":0,"passed_time":0.1858002547,"remaining_time":185.6144545},
{"learn":[14.23196558],"iteration":1,"passed_time":0.189800964,"remaining_time":94.71068105},
{"learn":[13.86674177],"iteration":2,"passed_time":0.1937700485,"remaining_time":64.39624611},
{"learn":[13.49946468],"iteration":3,"passed_time":0.1972330245,"remaining_time":49.1110231},
{"learn":[13.16661202],"iteration":4,"passed_time":0.2014514909,"remaining_time":40.08884668},
{"learn":[12.85632158],"iteration":5,"passed_time":0.2048759525,"remaining_time":33.94111613},
{"learn":[12.56784336],"iteration":6,"passed_time":0.2081916021,"remaining_time":29.53346585},
{"learn":[12.31617801],"iteration":7,"passed_time":0.2117609025,"remaining_time":26.25835192},
{"learn":[12.01509946],"iteration":8,"passed_time":0.2159037642,"remaining_time":23.77340337},
{"learn":[11.71512571],"iteration":9,"passed_time":0.2196030679,"remaining_time":21.74070372},
{"learn":[11.43264457],"iteration":10,"passed_time":0.2230567734,"remaining_time":20.05483172},
{"learn":[11.17973129],"iteration":11,"passed_time":0.2265976674,"remaining_time":18.65654128},
{"learn":[10.93746433],"iteration":12,"passed_time":0.2304616514,"remaining_time":17.49735769},
{"learn":[10.69387075],"iteration":13,"passed_time":0.2338634191,"remaining_time":16.47066652},
{"learn":[10.4615922],"iteration":14,"passed_time":0.2372544987,"remaining_time":15.57971208},
{"learn":[10.2299235],"iteration":15,"passed_time":0.2405587363,"remaining_time":14.79436228},
{"learn":[10.01419731],"iteration":16,"passed_time":0.2441534058,"remaining_time":14.11781164},
{"learn":[9.795856918],"iteration":17,"passed_time":0.2474694989,"remaining_time":13.50083599},
{"learn":[9.60040151],"iteration":18,"passed_time":0.2507450502,"remaining_time":12.94636285},
{"learn":[9.418664989],"iteration":19,"passed_time":0.2541528723,"remaining_time":12.45349074},
{"learn":[9.249278645],"iteration":20,"passed_time":0.2587976826,"remaining_time":12.06490149},
{"learn":[9.090113396],"iteration":21,"passed_time":0.2621660775,"remaining_time":11.65447381},
{"learn":[8.909548708],"iteration":22,"passed_time":0.2655993434,"remaining_time":11.28219819},
{"learn":[8.740140208],"iteration":23,"passed_time":0.2689841977,"remaining_time":10.93869071},
{"learn":[8.59377682],"iteration":24,"passed_time":0.2726931304,"remaining_time":10.63503208},
{"learn":[8.453885414],"iteration":25,"passed_time":0.2760847199,"remaining_time":10.34255835},
{"learn":[8.317732234],"iteration":26,"passed_time":0.279437474,"remaining_time":10.0700986},
{"learn":[8.180896085],"iteration":27,"passed_time":0.2824818508,"remaining_time":9.806155676},
{"learn":[8.053220863],"iteration":28,"passed_time":0.2862680134,"remaining_time":9.585042794},
{"learn":[7.924234474],"iteration":29,"passed_time":0.2896653503,"remaining_time":9.365846327},
{"learn":[7.818879511],"iteration":30,"passed_time":0.2930773122,"remaining_time":9.161029533},
{"learn":[7.719346395],"iteration":31,"passed_time":0.2963393747,"remaining_time":8.964266084},
{"learn":[7.624163594],"iteration":32,"passed_time":0.2997127063,"remaining_time":8.782490515},
{"learn":[7.524952543],"iteration":33,"passed_time":0.3031052709,"remaining_time":8.611755637},
{"learn":[7.424464745],"iteration":34,"passed_time":0.306364968,"remaining_time":8.446919833},
{"learn":[7.327482321],"iteration":35,"passed_time":0.3093471438,"remaining_time":8.283629074},
{"learn":[7.238666841],"iteration":36,"passed_time":0.3125047694,"remaining_time":8.133570079},
{"learn":[7.158842395],"iteration":37,"passed_time":0.3156837992,"remaining_time":7.991784601},
{"learn":[7.074348246],"iteration":38,"passed_time":0.3187554414,"remaining_time":7.854461005},
{"learn":[6.992269093],"iteration":39,"passed_time":0.321751454,"remaining_time":7.722034896},
{"learn":[6.925219745],"iteration":40,"passed_time":0.3240170207,"remaining_time":7.578837142},
{"learn":[6.86013671],"iteration":41,"passed_time":0.3262753767,"remaining_time":7.442185973},
{"learn":[6.786739622],"iteration":42,"passed_time":0.3282766462,"remaining_time":7.306063963},
{"learn":[6.73057926],"iteration":43,"passed_time":0.3302098247,"remaining_time":7.174558918},
{"learn":[6.666356486],"iteration":44,"passed_time":0.3318109999,"remaining_time":7.041766775},
{"learn":[6.606182832],"iteration":45,"passed_time":0.3334213798,"remaining_time":6.914869485},
{"learn":[6.547854615],"iteration":46,"passed_time":0.334970763,"remaining_time":6.792066748},
{"learn":[6.49240675],"iteration":47,"passed_time":0.3366357909,"remaining_time":6.676609853},
{"learn":[6.431317261],"iteration":48,"passed_time":0.3381377537,"remaining_time":6.56263273},
{"learn":[6.377586395],"iteration":49,"passed_time":0.339784415,"remaining_time":6.455903884},
{"learn":[6.327558015],"iteration":50,"passed_time":0.3412561272,"remaining_time":6.350040485},
{"learn":[6.282040317],"iteration":51,"passed_time":0.3428306363,"remaining_time":6.250066216},
{"learn":[6.237655841],"iteration":52,"passed_time":0.3442968963,"remaining_time":6.151870958},
{"learn":[6.192792003],"iteration":53,"passed_time":0.3457600444,"remaining_time":6.057203741},
{"learn":[6.150579347],"iteration":54,"passed_time":0.3472531785,"remaining_time":5.966440977},
{"learn":[6.115693845],"iteration":55,"passed_time":0.348750919,"remaining_time":5.878944064},
{"learn":[6.078780782],"iteration":56,"passed_time":0.3502566592,"remaining_time":5.79459701},
{"learn":[6.045146957],"iteration":57,"passed_time":0.3518480571,"remaining_time":5.714497755},
{"learn":[6.008080327],"iteration":58,"passed_time":0.3542094192,"remaining_time":5.649340059},
{"learn":[5.977575734],"iteration":59,"passed_time":0.3559093541,"remaining_time":5.575913215},
{"learn":[5.948036502],"iteration":60,"passed_time":0.3575499602,"remaining_time":5.503924796},
{"learn":[5.914888282],"iteration":61,"passed_time":0.3597856451,"remaining_time":5.44320863},
{"learn":[5.884957796],"iteration":62,"passed_time":0.3614568958,"remaining_time":5.375954148},
{"learn":[5.849539885],"iteration":63,"passed_time":0.3634596045,"remaining_time":5.315596716},
{"learn":[5.821387627],"iteration":64,"passed_time":0.3657330597,"remaining_time":5.260929398},
{"learn":[5.797012279],"iteration":65,"passed_time":0.3680496053,"remaining_time":5.208459566},
{"learn":[5.768685095],"iteration":66,"passed_time":0.3700171785,"remaining_time":5.152627276},
{"learn":[5.755484587],"iteration":67,"passed_time":0.3709034427,"remaining_time":5.08355895},
{"learn":[5.731887055],"iteration":68,"passed_time":0.3725431952,"remaining_time":5.026633547},
{"learn":[5.707148487],"iteration":69,"passed_time":0.374187617,"remaining_time":4.971349769},
{"learn":[5.685365039],"iteration":70,"passed_time":0.3761973821,"remaining_time":4.922357295},
{"learn":[5.663541834],"iteration":71,"passed_time":0.3777287456,"remaining_time":4.868503832},
{"learn":[5.638108797],"iteration":72,"passed_time":0.3791997266,"remaining_time":4.815317076},
{"learn":[5.619204893],"iteration":73,"passed_time":0.3806639884,"remaining_time":4.763443963},
{"learn":[5.598472793],"iteration":74,"passed_time":0.382121823,"remaining_time":4.712835817},
{"learn":[5.577007075],"iteration":75,"passed_time":0.3836021515,"remaining_time":4.663794578},
{"learn":[5.562637084],"iteration":76,"passed_time":0.3851231099,"remaining_time":4.61647572},
{"learn":[5.54729991],"iteration":77,"passed_time":0.3865530007,"remaining_time":4.5692547},
{"learn":[5.530737623],"iteration":78,"passed_time":0.3879799841,"remaining_time":4.523159056},
{"learn":[5.513704873],"iteration":79,"passed_time":0.3893924397,"remaining_time":4.478013056},
{"learn":[5.501575529],"iteration":80,"passed_time":0.3907812748,"remaining_time":4.433678908},
{"learn":[5.484080734],"iteration":81,"passed_time":0.3921727574,"remaining_time":4.390421845},
{"learn":[5.472178894],"iteration":82,"passed_time":0.393630139,"remaining_time":4.348901656},
{"learn":[5.458923342],"iteration":83,"passed_time":0.3951106743,"remaining_time":4.308587829},
{"learn":[5.451382371],"iteration":84,"passed_time":0.3961591633,"remaining_time":4.264536876},
{"learn":[5.441410748],"iteration":85,"passed_time":0.3976967151,"remaining_time":4.226683693},
{"learn":[5.434047468],"iteration":86,"passed_time":0.3987256593,"remaining_time":4.184327895},
{"learn":[5.422107497],"iteration":87,"passed_time":0.4002593792,"remaining_time":4.148142658},
{"learn":[5.40731265],"iteration":88,"passed_time":0.4016910661,"remaining_time":4.111691699},
{"learn":[5.396360181],"iteration":89,"passed_time":0.4031056697,"remaining_time":4.075846215},
{"learn":[5.383793239],"iteration":90,"passed_time":0.4045454163,"remaining_time":4.041008609},
{"learn":[5.369605034],"iteration":91,"passed_time":0.4059679561,"remaining_time":4.006727219},
{"learn":[5.357467333],"iteration":92,"passed_time":0.4073408649,"remaining_time":3.972668435},
{"learn":[5.341109968],"iteration":93,"passed_time":0.4088154861,"remaining_time":3.94028543},
{"learn":[5.330529276],"iteration":94,"passed_time":0.4103055261,"remaining_time":3.908700012},
{"learn":[5.319862075],"iteration":95,"passed_time":0.4118553335,"remaining_time":3.878304391},
{"learn":[5.313052243],"iteration":96,"passed_time":0.4133479336,"remaining_time":3.84797097},
{"learn":[5.299677207],"iteration":97,"passed_time":0.414827061,"remaining_time":3.818102133},
{"learn":[5.287546698],"iteration":98,"passed_time":0.4163511641,"remaining_time":3.78921615},
{"learn":[5.279803754],"iteration":99,"passed_time":0.4177773393,"remaining_time":3.759996054},
{"learn":[5.272254612],"iteration":100,"passed_time":0.4191780043,"remaining_time":3.731099266},
{"learn":[5.268813888],"iteration":101,"passed_time":0.4199555475,"remaining_time":3.697255703},
{"learn":[5.258113767],"iteration":102,"passed_time":0.4213576173,"remaining_time":3.669493036},
{"learn":[5.251018576],"iteration":103,"passed_time":0.4227296818,"remaining_time":3.641978797},
{"learn":[5.24171237],"iteration":104,"passed_time":0.4241775082,"remaining_time":3.615608284},
{"learn":[5.233984943],"iteration":105,"passed_time":0.4258475085,"remaining_time":3.591581817},
{"learn":[5.226240449],"iteration":106,"passed_time":0.4273221681,"remaining_time":3.566342955},
{"learn":[5.220541644],"iteration":107,"passed_time":0.4287685609,"remaining_time":3.541310707},
{"learn":[5.211712096],"iteration":108,"passed_time":0.4302606639,"remaining_time":3.517084877},
{"learn":[5.203388597],"iteration":109,"passed_time":0.4317415922,"remaining_time":3.493181973},
{"learn":[5.196026544],"iteration":110,"passed_time":0.4331483805,"remaining_time":3.469089282},
{"learn":[5.188716772],"iteration":111,"passed_time":0.4345210143,"remaining_time":3.445130899},
{"learn":[5.182163132],"iteration":112,"passed_time":0.4358905667,"remaining_time":3.421548077},
{"learn":[5.17764747],"iteration":113,"passed_time":0.4372539565,"remaining_time":3.398307066},
{"learn":[5.170548056],"iteration":114,"passed_time":0.4386993831,"remaining_time":3.376077861},
{"learn":[5.165901827],"iteration":115,"passed_time":0.4401801995,"remaining_time":3.354476693},
{"learn":[5.160333668],"iteration":116,"passed_time":0.4417309154,"remaining_time":3.333746994},
{"learn":[5.148953243],"iteration":117,"passed_time":0.4432352178,"remaining_time":3.312995442},
{"learn":[5.144729126],"iteration":118,"passed_time":0.4443847898,"remaining_time":3.289941175},
{"learn":[5.139939946],"iteration":119,"passed_time":0.4458553707,"remaining_time":3.269606052},
{"learn":[5.132898872],"iteration":120,"passed_time":0.4473263902,"remaining_time":3.249585925},
{"learn":[5.129073077],"iteration":121,"passed_time":0.4488706499,"remaining_time":3.230396972},
{"learn":[5.127123916],"iteration":122,"passed_time":0.4496567725,"remaining_time":3.206089345},
{"learn":[5.121282057],"iteration":123,"passed_time":0.451003346,"remaining_time":3.186120412},
{"learn":[5.114489821],"iteration":124,"passed_time":0.4523979204,"remaining_time":3.166785443},
{"learn":[5.107777291],"iteration":125,"passed_time":0.4537633612,"remaining_time":3.147533156},
{"learn":[5.103518754],"iteration":126,"passed_time":0.4552944256,"remaining_time":3.129701051},
{"learn":[5.101133351],"iteration":127,"passed_time":0.456273272,"remaining_time":3.108361666},
{"learn":[5.096462705],"iteration":128,"passed_time":0.4577273919,"remaining_time":3.090546964},
{"learn":[5.08562082],"iteration":129,"passed_time":0.4592386957,"remaining_time":3.073366656},
{"learn":[5.080483682],"iteration":130,"passed_time":0.4607551087,"remaining_time":3.056459461},
{"learn":[5.07437499],"iteration":131,"passed_time":0.4622559233,"remaining_time":3.03968289},
{"learn":[5.070683732],"iteration":132,"passed_time":0.4636966706,"remaining_time":3.022744462},
{"learn":[5.06432037],"iteration":133,"passed_time":0.4651220432,"remaining_time":3.005937981},
{"learn":[5.057436484],"iteration":134,"passed_time":0.4665213259,"remaining_time":2.989192199},
{"learn":[5.053254656],"iteration":135,"passed_time":0.4679323638,"remaining_time":2.972746782},
{"learn":[5.04801663],"iteration":136,"passed_time":0.4696305921,"remaining_time":2.958329934},
{"learn":[5.045680836],"iteration":137,"passed_time":0.471495888,"remaining_time":2.945140981},
{"learn":[5.041857933],"iteration":138,"passed_time":0.4733969922,"remaining_time":2.932336765},
{"learn":[5.035264888],"iteration":139,"passed_time":0.4750668537,"remaining_time":2.918267816},
{"learn":[5.028771948],"iteration":140,"passed_time":0.4774453729,"remaining_time":2.908692024},
{"learn":[5.024912247],"iteration":141,"passed_time":0.4805755077,"remaining_time":2.903759054},
{"learn":[5.02239068],"iteration":142,"passed_time":0.4822654056,"remaining_time":2.890219948},
{"learn":[5.017110572],"iteration":143,"passed_time":0.4841181368,"remaining_time":2.877813369},
{"learn":[5.010707886],"iteration":144,"passed_time":0.4861638906,"remaining_time":2.866690527},
{"learn":[5.004389868],"iteration":145,"passed_time":0.4878257405,"remaining_time":2.853446455},
{"learn":[4.997628683],"iteration":146,"passed_time":0.489525511,"remaining_time":2.840580006},
{"learn":[4.991497851],"iteration":147,"passed_time":0.4911946365,"remaining_time":2.827688043},
{"learn":[4.988345253],"iteration":148,"passed_time":0.4928919876,"remaining_time":2.815107929},
{"learn":[4.98460423],"iteration":149,"passed_time":0.4946114393,"remaining_time":2.802798156},
{"learn":[4.982441783],"iteration":150,"passed_time":0.4963658357,"remaining_time":2.790825129},
{"learn":[4.977461771],"iteration":151,"passed_time":0.498290228,"remaining_time":2.779934956},
{"learn":[4.973601586],"iteration":152,"passed_time":0.5009406402,"remaining_time":2.773181191},
{"learn":[4.968328804],"iteration":153,"passed_time":0.5027511319,"remaining_time":2.761866607},
{"learn":[4.9640736],"iteration":154,"passed_time":0.5043986964,"remaining_time":2.749786441},
{"learn":[4.960865882],"iteration":155,"passed_time":0.5060700789,"remaining_time":2.737968889},
{"learn":[4.957014156],"iteration":156,"passed_time":0.5076986538,"remaining_time":2.726050734},
{"learn":[4.952244852],"iteration":157,"passed_time":0.5093712275,"remaining_time":2.714497301},
{"learn":[4.949695675],"iteration":158,"passed_time":0.5112218684,"remaining_time":2.704010008},
{"learn":[4.946584698],"iteration":159,"passed_time":0.5128289601,"remaining_time":2.692352041},
{"learn":[4.940192834],"iteration":160,"passed_time":0.5145583614,"remaining_time":2.681456306},
{"learn":[4.936727994],"iteration":161,"passed_time":0.5162157553,"remaining_time":2.670301253},
{"learn":[4.932342063],"iteration":162,"passed_time":0.5180797045,"remaining_time":2.660323391},
{"learn":[4.925830838],"iteration":163,"passed_time":0.5197517943,"remaining_time":2.649466464},
{"learn":[4.922571773],"iteration":164,"passed_time":0.5215117661,"remaining_time":2.639165604},
{"learn":[4.918395814],"iteration":165,"passed_time":0.5231565439,"remaining_time":2.628388901},
{"learn":[4.911142452],"iteration":166,"passed_time":0.5247531111,"remaining_time":2.617481087},
{"learn":[4.908276131],"iteration":167,"passed_time":0.5269545757,"remaining_time":2.609679804},
{"learn":[4.904584645],"iteration":168,"passed_time":0.5355859286,"remaining_time":2.633561578},
{"learn":[4.89795517],"iteration":169,"passed_time":0.5386818972,"remaining_time":2.630035145},
{"learn":[4.895556491],"iteration":170,"passed_time":0.5406264072,"remaining_time":2.62093153},
{"learn":[4.890591233],"iteration":171,"passed_time":0.5423101288,"remaining_time":2.610655736},
{"learn":[4.884629277],"iteration":172,"passed_time":0.5449853377,"remaining_time":2.605218927},
{"learn":[4.880550786],"iteration":173,"passed_time":0.546672578,"remaining_time":2.595123847},
{"learn":[4.876384842],"iteration":174,"passed_time":0.5482702233,"remaining_time":2.584702481},
{"learn":[4.872638238],"iteration":175,"passed_time":0.5499744995,"remaining_time":2.574880612},
{"learn":[4.869137118],"iteration":176,"passed_time":0.5515841923,"remaining_time":2.564710679},
{"learn":[4.863587157],"iteration":177,"passed_time":0.5533300262,"remaining_time":2.555265627},
{"learn":[4.858028614],"iteration":178,"passed_time":0.5551726463,"remaining_time":2.546350517},
{"learn":[4.853838176],"iteration":179,"passed_time":0.5610984254,"remaining_time":2.556115049},
{"learn":[4.853462329],"iteration":180,"passed_time":0.5620707828,"remaining_time":2.543292658},
{"learn":[4.851573196],"iteration":181,"passed_time":0.5640868721,"remaining_time":2.535291546},
{"learn":[4.848442087],"iteration":182,"passed_time":0.5659092971,"remaining_time":2.526491233},
{"learn":[4.845547104],"iteration":183,"passed_time":0.567854918,"remaining_time":2.518313114},
{"learn":[4.839868817],"iteration":184,"passed_time":0.5705876012,"remaining_time":2.513669703},
{"learn":[4.836336958],"iteration":185,"passed_time":0.5723772354,"remaining_time":2.504919729},
{"learn":[4.831124789],"iteration":186,"passed_time":0.575804786,"remaining_time":2.503365193},
{"learn":[4.827407333],"iteration":187,"passed_time":0.5778204359,"remaining_time":2.495692521},
{"learn":[4.824088918],"iteration":188,"passed_time":0.5793573295,"remaining_time":2.486025366},
{"learn":[4.820934539],"iteration":189,"passed_time":0.580811143,"remaining_time":2.47608961},
{"learn":[4.816975227],"iteration":190,"passed_time":0.5822797442,"remaining_time":2.466305304},
{"learn":[4.812340486],"iteration":191,"passed_time":0.5837190362,"remaining_time":2.456484277},
{"learn":[4.806402747],"iteration":192,"passed_time":0.585211828,"remaining_time":2.446973809},
{"learn":[4.801521788],"iteration":193,"passed_time":0.5866154331,"remaining_time":2.437175459},
{"learn":[4.797601172],"iteration":194,"passed_time":0.5888978943,"remaining_time":2.431091307},
{"learn":[4.792694629],"iteration":195,"passed_time":0.5913384068,"remaining_time":2.425694281},
{"learn":[4.789794613],"iteration":196,"passed_time":0.5929946284,"remaining_time":2.417130389},
{"learn":[4.785367055],"iteration":197,"passed_time":0.5944758925,"remaining_time":2.407927605},
{"learn":[4.780376856],"iteration":198,"passed_time":0.5959683884,"remaining_time":2.398847634},
{"learn":[4.776691261],"iteration":199,"passed_time":0.5974330504,"remaining_time":2.389732202},
{"learn":[4.773470753],"iteration":200,"passed_time":0.5989504456,"remaining_time":2.380902517},
{"learn":[4.77207327],"iteration":201,"passed_time":0.6003939567,"remaining_time":2.371853354},
{"learn":[4.767347177],"iteration":202,"passed_time":0.6021549668,"remaining_time":2.364125658},
{"learn":[4.763983068],"iteration":203,"passed_time":0.6047797316,"remaining_time":2.359826796},
{"learn":[4.761588849],"iteration":204,"passed_time":0.6066727436,"remaining_time":2.352706494},
{"learn":[4.758558086],"iteration":205,"passed_time":0.6081383116,"remaining_time":2.343989415},
{"learn":[4.753678804],"iteration":206,"passed_time":0.6096492884,"remaining_time":2.335516356},
{"learn":[4.746510889],"iteration":207,"passed_time":0.6111376156,"remaining_time":2.327023998},
{"learn":[4.744840601],"iteration":208,"passed_time":0.6125496959,"remaining_time":2.318310093},
{"learn":[4.741702222],"iteration":209,"passed_time":0.6140571054,"remaining_time":2.310024349},
{"learn":[4.739352853],"iteration":210,"passed_time":0.6155491306,"remaining_time":2.301745327},
{"learn":[4.735539287],"iteration":211,"passed_time":0.6177618113,"remaining_time":2.296208997},
{"learn":[4.730726751],"iteration":212,"passed_time":0.6196201299,"remaining_time":2.289394565},
{"learn":[4.726416092],"iteration":213,"passed_time":0.6216100647,"remaining_time":2.283109864},
{"learn":[4.721293082],"iteration":214,"passed_time":0.623179506,"remaining_time":2.275329824},
{"learn":[4.718443695],"iteration":215,"passed_time":0.6246672928,"remaining_time":2.267310915},
{"learn":[4.711627962],"iteration":216,"passed_time":0.6261754263,"remaining_time":2.259425617},
{"learn":[4.709790764],"iteration":217,"passed_time":0.6276181846,"remaining_time":2.251364313},
{"learn":[4.706913073],"iteration":218,"passed_time":0.6290580691,"remaining_time":2.243353205},
{"learn":[4.703846389],"iteration":219,"passed_time":0.630566019,"remaining_time":2.235643158},
{"learn":[4.701001135],"iteration":220,"passed_time":0.6333548002,"remaining_time":2.232504024},
{"learn":[4.700380864],"iteration":221,"passed_time":0.63522075,"remaining_time":2.22613398},
{"learn":[4.695837486],"iteration":222,"passed_time":0.6369106475,"remaining_time":2.219190911},
{"learn":[4.691242996],"iteration":223,"passed_time":0.6385243609,"remaining_time":2.212030822},
{"learn":[4.690284609],"iteration":224,"passed_time":0.6402078772,"remaining_time":2.205160466},
{"learn":[4.68827119],"iteration":225,"passed_time":0.6418738228,"remaining_time":2.198275835},
{"learn":[4.686922425],"iteration":226,"passed_time":0.6436692031,"remaining_time":2.191877947},
{"learn":[4.686085874],"iteration":227,"passed_time":0.6454881679,"remaining_time":2.185600288},
{"learn":[4.683230741],"iteration":228,"passed_time":0.6486444945,"remaining_time":2.183864215},
{"learn":[4.6773487],"iteration":229,"passed_time":0.6504560622,"remaining_time":2.177613773},
{"learn":[4.671462906],"iteration":230,"passed_time":0.6528078563,"remaining_time":2.17320018},
{"learn":[4.664799601],"iteration":231,"passed_time":0.6556262423,"remaining_time":2.17034894},
{"learn":[4.660979386],"iteration":232,"passed_time":0.6578699569,"remaining_time":2.165606253},
{"learn":[4.656281279],"iteration":233,"passed_time":0.6593984002,"remaining_time":2.158543481},
{"learn":[4.651997094],"iteration":234,"passed_time":0.6620585223,"remaining_time":2.155211785},
{"learn":[4.650151977],"iteration":235,"passed_time":0.6635845345,"remaining_time":2.14821434},
{"learn":[4.648478046],"iteration":236,"passed_time":0.6650172204,"remaining_time":2.140962613},
{"learn":[4.646364602],"iteration":237,"passed_time":0.6664780545,"remaining_time":2.133849906},
{"learn":[4.642635873],"iteration":238,"passed_time":0.6679411426,"remaining_time":2.126791671},
{"learn":[4.640860821],"iteration":239,"passed_time":0.669392161,"remaining_time":2.119741843},
{"learn":[4.639446822],"iteration":240,"passed_time":0.6707464446,"remaining_time":2.112433824},
{"learn":[4.637120072],"iteration":241,"passed_time":0.6721804214,"remaining_time":2.105424626},
{"learn":[4.633769267],"iteration":242,"passed_time":0.6736348115,"remaining_time":2.098524906},
{"learn":[4.630491517],"iteration":243,"passed_time":0.6758389004,"remaining_time":2.093992659},
{"learn":[4.627813333],"iteration":244,"passed_time":0.6773429198,"remaining_time":2.087322059},
{"learn":[4.622496304],"iteration":245,"passed_time":0.678822489,"remaining_time":2.080618523},
{"learn":[4.618979301],"iteration":246,"passed_time":0.6802960141,"remaining_time":2.073938861},
{"learn":[4.616563458],"iteration":247,"passed_time":0.6817502133,"remaining_time":2.067242582},
{"learn":[4.614759385],"iteration":248,"passed_time":0.6832194849,"remaining_time":2.060633868},
{"learn":[4.61251363],"iteration":249,"passed_time":0.6845877199,"remaining_time":2.05376316},
{"learn":[4.608796693],"iteration":250,"passed_time":0.6859977997,"remaining_time":2.047061163},
{"learn":[4.60847774],"iteration":251,"passed_time":0.6873399857,"remaining_time":2.04019964},
{"learn":[4.605195659],"iteration":252,"passed_time":0.6886922632,"remaining_time":2.033411544},
{"learn":[4.60103766],"iteration":253,"passed_time":0.6903204946,"remaining_time":2.027476728},
{"learn":[4.599325598],"iteration":254,"passed_time":0.691796923,"remaining_time":2.021132187},
{"learn":[4.597012808],"iteration":255,"passed_time":0.6932398849,"remaining_time":2.014728415},
{"learn":[4.594161533],"iteration":256,"passed_time":0.6947826781,"remaining_time":2.008651867},
{"learn":[4.592197259],"iteration":257,"passed_time":0.6962146616,"remaining_time":2.002291779},
{"learn":[4.58952828],"iteration":258,"passed_time":0.697682704,"remaining_time":1.99607291},
{"learn":[4.585816572],"iteration":259,"passed_time":0.6991224635,"remaining_time":1.989810088},
{"learn":[4.582934052],"iteration":260,"passed_time":0.7004908445,"remaining_time":1.983382123},
{"learn":[4.582234842],"iteration":261,"passed_time":0.701857573,"remaining_time":1.976988125},
{"learn":[4.57571562],"iteration":262,"passed_time":0.7034204174,"remaining_time":1.97118193},
{"learn":[4.571197349],"iteration":263,"passed_time":0.704843577,"remaining_time":1.965018457},
{"learn":[4.56723703],"iteration":264,"passed_time":0.7062557824,"remaining_time":1.958860378},
{"learn":[4.560335567],"iteration":265,"passed_time":0.7077745527,"remaining_time":1.953032036},
{"learn":[4.554709345],"iteration":266,"passed_time":0.7092801493,"remaining_time":1.94719981},
{"learn":[4.552806306],"iteration":267,"passed_time":0.7107147002,"remaining_time":1.941205823},
{"learn":[4.550766241],"iteration":268,"passed_time":0.7121548814,"remaining_time":1.935261034},
{"learn":[4.549216045],"iteration":269,"passed_time":0.7135426741,"remaining_time":1.929207971},
{"learn":[4.547687452],"iteration":270,"passed_time":0.7149971026,"remaining_time":1.92336859},
{"learn":[4.545642435],"iteration":271,"passed_time":0.7163639097,"remaining_time":1.917326935},
{"learn":[4.543930359],"iteration":272,"passed_time":0.7178377291,"remaining_time":1.911604502},
{"learn":[4.541029943],"iteration":273,"passed_time":0.7193534517,"remaining_time":1.906024109},
{"learn":[4.537781449],"iteration":274,"passed_time":0.7208240759,"remaining_time":1.900354382},
{"learn":[4.53066128],"iteration":275,"passed_time":0.7222951996,"remaining_time":1.894716393},
{"learn":[4.526763956],"iteration":276,"passed_time":0.723760127,"remaining_time":1.889092317},
{"learn":[4.522036004],"iteration":277,"passed_time":0.7252465564,"remaining_time":1.883554006},
{"learn":[4.515307629],"iteration":278,"passed_time":0.7267463607,"remaining_time":1.878079305},
{"learn":[4.51109143],"iteration":279,"passed_time":0.7282989304,"remaining_time":1.872768678},
{"learn":[4.508233494],"iteration":280,"passed_time":0.7297185196,"remaining_time":1.867144539},
{"learn":[4.502555629],"iteration":281,"passed_time":0.7312537558,"remaining_time":1.861844669},
{"learn":[4.500081355],"iteration":282,"passed_time":0.7327365979,"remaining_time":1.85643866},
{"learn":[4.495281743],"iteration":283,"passed_time":0.7342296069,"remaining_time":1.85108591},
{"learn":[4.492138869],"iteration":284,"passed_time":0.7356971426,"remaining_time":1.84569634},
{"learn":[4.491708261],"iteration":285,"passed_time":0.7371438657,"remaining_time":1.840282238},
{"learn":[4.489398865],"iteration":286,"passed_time":0.7385771169,"remaining_time":1.834862315},
{"learn":[4.485796373],"iteration":287,"passed_time":0.7399702497,"remaining_time":1.829370895},
{"learn":[4.479542205],"iteration":288,"passed_time":0.7413294684,"remaining_time":1.823824402},
{"learn":[4.475986993],"iteration":289,"passed_time":0.742761294,"remaining_time":1.818484547},
{"learn":[4.468661855],"iteration":290,"passed_time":0.7442055412,"remaining_time":1.813201817},
{"learn":[4.463785664],"iteration":291,"passed_time":0.7464491548,"remaining_time":1.809883567},
{"learn":[4.460445831],"iteration":292,"passed_time":0.7479237519,"remaining_time":1.80471704},
{"learn":[4.45692492],"iteration":293,"passed_time":0.7494612757,"remaining_time":1.799726737},
{"learn":[4.454031688],"iteration":294,"passed_time":0.7509583763,"remaining_time":1.794663238},
{"learn":[4.451672391],"iteration":295,"passed_time":0.7524405289,"remaining_time":1.789588285},
{"learn":[4.45031553],"iteration":296,"passed_time":0.7539182162,"remaining_time":1.784526956},
{"learn":[4.446782666],"iteration":297,"passed_time":0.7554098117,"remaining_time":1.779522442},
{"learn":[4.444369689],"iteration":298,"passed_time":0.7567856126,"remaining_time":1.774269948},
{"learn":[4.44411683],"iteration":299,"passed_time":0.7581011634,"remaining_time":1.768902715},
{"learn":[4.440876943],"iteration":300,"passed_time":0.7595182918,"remaining_time":1.763798292},
{"learn":[4.439336453],"iteration":301,"passed_time":0.7623196362,"remaining_time":1.76191757},
{"learn":[4.436666901],"iteration":302,"passed_time":0.7646942566,"remaining_time":1.759049164},
{"learn":[4.433043336],"iteration":303,"passed_time":0.766965298,"remaining_time":1.755946866},
{"learn":[4.431419305],"iteration":304,"passed_time":0.7689074078,"remaining_time":1.752100487},
{"learn":[4.428859646],"iteration":305,"passed_time":0.7707461214,"remaining_time":1.748032053},
{"learn":[4.424552441],"iteration":306,"passed_time":0.7723559889,"remaining_time":1.743461565},
{"learn":[4.422706391],"iteration":307,"passed_time":0.7737992771,"remaining_time":1.738536038},
{"learn":[4.421427994],"iteration":308,"passed_time":0.7752334713,"remaining_time":1.733612714},
{"learn":[4.418733158],"iteration":309,"passed_time":0.7767025953,"remaining_time":1.728789648},
{"learn":[4.415656941],"iteration":310,"passed_time":0.7781991627,"remaining_time":1.724048949},
{"learn":[4.410747417],"iteration":311,"passed_time":0.7799355859,"remaining_time":1.719857959},
{"learn":[4.408126521],"iteration":312,"passed_time":0.7813806452,"remaining_time":1.715043141},
{"learn":[4.407843853],"iteration":313,"passed_time":0.7827326405,"remaining_time":1.710046469},
{"learn":[4.405219398],"iteration":314,"passed_time":0.7841463573,"remaining_time":1.705207158},
{"learn":[4.402708465],"iteration":315,"passed_time":0.7855298059,"remaining_time":1.70032401},
{"learn":[4.40104971],"iteration":316,"passed_time":0.7869876998,"remaining_time":1.695623341},
{"learn":[4.400830038],"iteration":317,"passed_time":0.7883945523,"remaining_time":1.6908336},
{"learn":[4.39784288],"iteration":318,"passed_time":0.7898658708,"remaining_time":1.68620269},
{"learn":[4.393741845],"iteration":319,"passed_time":0.7913573588,"remaining_time":1.681634388},
{"learn":[4.393425936],"iteration":320,"passed_time":0.7927430148,"remaining_time":1.676861393},
{"learn":[4.390505974],"iteration":321,"passed_time":0.7942312787,"remaining_time":1.672325487},
{"learn":[4.390305136],"iteration":322,"passed_time":0.7955595293,"remaining_time":1.667473069},
{"learn":[4.38568203],"iteration":323,"passed_time":0.7970245874,"remaining_time":1.662927843},
{"learn":[4.383057135],"iteration":324,"passed_time":0.7984576958,"remaining_time":1.658335214},
{"learn":[4.380662684],"iteration":325,"passed_time":0.7999118076,"remaining_time":1.653805394},
{"learn":[4.37805727],"iteration":326,"passed_time":0.8012886565,"remaining_time":1.649135369},
{"learn":[4.373708319],"iteration":327,"passed_time":0.8027975678,"remaining_time":1.644755993},
{"learn":[4.36887921],"iteration":328,"passed_time":0.8042998361,"remaining_time":1.640380517},
{"learn":[4.367895929],"iteration":329,"passed_time":0.8057448979,"remaining_time":1.635906308},
{"learn":[4.362140573],"iteration":330,"passed_time":0.8072417123,"remaining_time":1.631555002},
{"learn":[4.361931924],"iteration":331,"passed_time":0.8086568162,"remaining_time":1.627056486},
{"learn":[4.359656377],"iteration":332,"passed_time":0.8100710718,"remaining_time":1.622574789},
{"learn":[4.354281355],"iteration":333,"passed_time":0.8116007017,"remaining_time":1.618341519},
{"learn":[4.348589447],"iteration":334,"passed_time":0.8129986245,"remaining_time":1.613862941},
{"learn":[4.346355698],"iteration":335,"passed_time":0.8143808639,"remaining_time":1.609371707},
{"learn":[4.343894047],"iteration":336,"passed_time":0.8157932962,"remaining_time":1.604958325},
{"learn":[4.341561356],"iteration":337,"passed_time":0.8172295822,"remaining_time":1.600609418},
{"learn":[4.338869061],"iteration":338,"passed_time":0.8187109675,"remaining_time":1.596365633},
{"learn":[4.333720063],"iteration":339,"passed_time":0.8202279064,"remaining_time":1.592207112},
{"learn":[4.330892223],"iteration":340,"passed_time":0.8217431592,"remaining_time":1.588060827},
{"learn":[4.328311474],"iteration":341,"passed_time":0.8232130112,"remaining_time":1.583842577},
{"learn":[4.324580133],"iteration":342,"passed_time":0.8249522062,"remaining_time":1.580156267},
{"learn":[4.323354432],"iteration":343,"passed_time":0.8263721859,"remaining_time":1.575872541},
{"learn":[4.323159553],"iteration":344,"passed_time":0.8276783683,"remaining_time":1.571389366},
{"learn":[4.318639682],"iteration":345,"passed_time":0.8290991482,"remaining_time":1.567141165},
{"learn":[4.312712208],"iteration":346,"passed_time":0.8305032,"remaining_time":1.56287778},
{"learn":[4.311461062],"iteration":347,"passed_time":0.83189136,"remaining_time":1.558601054},
{"learn":[4.311178356],"iteration":348,"passed_time":0.8332676572,"remaining_time":1.554318753},
{"learn":[4.311102505],"iteration":349,"passed_time":0.83465437,"remaining_time":1.550072401},
{"learn":[4.310232308],"iteration":350,"passed_time":0.8360529021,"remaining_time":1.545864198},
{"learn":[4.305128197],"iteration":351,"passed_time":0.8376404714,"remaining_time":1.542019959},
{"learn":[4.304595496],"iteration":352,"passed_time":0.8392243584,"remaining_time":1.538181756},
{"learn":[4.3004992],"iteration":353,"passed_time":0.8408263053,"remaining_time":1.534389246},
{"learn":[4.297581524],"iteration":354,"passed_time":0.8423164584,"remaining_time":1.53040596},
{"learn":[4.297355825],"iteration":355,"passed_time":0.843742818,"remaining_time":1.526321278},
{"learn":[4.295758715],"iteration":356,"passed_time":0.8452581405,"remaining_time":1.522411721},
{"learn":[4.292500657],"iteration":357,"passed_time":0.8467810068,"remaining_time":1.518529068},
{"learn":[4.290797586],"iteration":358,"passed_time":0.8482170852,"remaining_time":1.514504601},
{"learn":[4.286410608],"iteration":359,"passed_time":0.8498183149,"remaining_time":1.510788115},
{"learn":[4.280278245],"iteration":360,"passed_time":0.8516400515,"remaining_time":1.507473664},
{"learn":[4.279941283],"iteration":361,"passed_time":0.8533302432,"remaining_time":1.503935622},
{"learn":[4.274426275],"iteration":362,"passed_time":0.854910017,"remaining_time":1.500213997},
{"learn":[4.273567658],"iteration":363,"passed_time":0.8565401273,"remaining_time":1.496592091},
{"learn":[4.269488271],"iteration":364,"passed_time":0.858317538,"remaining_time":1.493237361},
{"learn":[4.266838205],"iteration":365,"passed_time":0.8598670812,"remaining_time":1.489496529},
{"learn":[4.263456509],"iteration":366,"passed_time":0.8613980691,"remaining_time":1.485735634},
{"learn":[4.260360204],"iteration":367,"passed_time":0.8628770705,"remaining_time":1.481897578},
{"learn":[4.255120549],"iteration":368,"passed_time":0.8644300383,"remaining_time":1.478198792},
{"learn":[4.252582211],"iteration":369,"passed_time":0.8661674079,"remaining_time":1.474825586},
{"learn":[4.247857931],"iteration":370,"passed_time":0.8677710342,"remaining_time":1.471234449},
{"learn":[4.245288911],"iteration":371,"passed_time":0.8693948304,"remaining_time":1.467688047},
{"learn":[4.24048515],"iteration":372,"passed_time":0.8709376332,"remaining_time":1.464015807},
{"learn":[4.2378365],"iteration":373,"passed_time":0.872689811,"remaining_time":1.460705406},
{"learn":[4.236751063],"iteration":374,"passed_time":0.8743319902,"remaining_time":1.457219984},
{"learn":[4.233240093],"iteration":375,"passed_time":0.8759519746,"remaining_time":1.453707532},
{"learn":[4.230358421],"iteration":376,"passed_time":0.8774519505,"remaining_time":1.450006804},
{"learn":[4.225853583],"iteration":377,"passed_time":0.8790258987,"remaining_time":1.446439442},
{"learn":[4.224702126],"iteration":378,"passed_time":0.8805304991,"remaining_time":1.442768971},
{"learn":[4.224361982],"iteration":379,"passed_time":0.8821163333,"remaining_time":1.439242439},
{"learn":[4.223787954],"iteration":380,"passed_time":0.8836020371,"remaining_time":1.435563415},
{"learn":[4.22144054],"iteration":381,"passed_time":0.8851934899,"remaining_time":1.432066955},
{"learn":[4.217739335],"iteration":382,"passed_time":0.8872177813,"remaining_time":1.429277731},
{"learn":[4.215611665],"iteration":383,"passed_time":0.889214153,"remaining_time":1.426447704},
{"learn":[4.210236863],"iteration":384,"passed_time":0.8913314251,"remaining_time":1.423815134},
{"learn":[4.208454294],"iteration":385,"passed_time":0.8934659902,"remaining_time":1.421212741},
{"learn":[4.207446501],"iteration":386,"passed_time":0.8950989955,"remaining_time":1.417818305},
{"learn":[4.204985442],"iteration":387,"passed_time":0.8967307355,"remaining_time":1.414430954},
{"learn":[4.202796622],"iteration":388,"passed_time":0.8983934209,"remaining_time":1.411101234},
{"learn":[4.199774004],"iteration":389,"passed_time":0.9000330395,"remaining_time":1.407743985},
{"learn":[4.199458358],"iteration":390,"passed_time":0.9015869858,"remaining_time":1.404262083},
{"learn":[4.19751254],"iteration":391,"passed_time":0.9033263191,"remaining_time":1.401077556},
{"learn":[4.195201346],"iteration":392,"passed_time":0.9050381075,"remaining_time":1.39785784},
{"learn":[4.190593508],"iteration":393,"passed_time":0.9066648455,"remaining_time":1.394514965},
{"learn":[4.187212054],"iteration":394,"passed_time":0.9088772111,"remaining_time":1.392077754},
{"learn":[4.184984466],"iteration":395,"passed_time":0.9110438825,"remaining_time":1.389571982},
{"learn":[4.182832144],"iteration":396,"passed_time":0.912907647,"remaining_time":1.386607837},
{"learn":[4.179752812],"iteration":397,"passed_time":0.914659634,"remaining_time":1.38348015},
{"learn":[4.17878934],"iteration":398,"passed_time":0.9163061537,"remaining_time":1.380200497},
{"learn":[4.174548229],"iteration":399,"passed_time":0.9179822209,"remaining_time":1.376973331},
{"learn":[4.168872556],"iteration":400,"passed_time":0.9196462617,"remaining_time":1.373735937},
{"learn":[4.163926494],"iteration":401,"passed_time":0.9213719222,"remaining_time":1.370598033},
{"learn":[4.159485076],"iteration":402,"passed_time":0.9230130481,"remaining_time":1.36734191},
{"learn":[4.155926102],"iteration":403,"passed_time":0.9245893168,"remaining_time":1.363998101},
{"learn":[4.153540115],"iteration":404,"passed_time":0.9263173667,"remaining_time":1.360886008},
{"learn":[4.150983044],"iteration":405,"passed_time":0.9278204712,"remaining_time":1.357451625},
{"learn":[4.146539132],"iteration":406,"passed_time":0.9294562003,"remaining_time":1.354219967},
{"learn":[4.144869174],"iteration":407,"passed_time":0.9310673395,"remaining_time":1.350960453},
{"learn":[4.142825962],"iteration":408,"passed_time":0.9326637888,"remaining_time":1.347687773},
{"learn":[4.142467378],"iteration":409,"passed_time":0.934177543,"remaining_time":1.344304269},
{"learn":[4.141800768],"iteration":410,"passed_time":0.9357084599,"remaining_time":1.34095446},
{"learn":[4.140107084],"iteration":411,"passed_time":0.9372636001,"remaining_time":1.337648051},
{"learn":[4.136243196],"iteration":412,"passed_time":0.9387769317,"remaining_time":1.3342907},
{"learn":[4.133618439],"iteration":413,"passed_time":0.9403873726,"remaining_time":1.331079711},
{"learn":[4.131053025],"iteration":414,"passed_time":0.9419685122,"remaining_time":1.327835132},
{"learn":[4.128379975],"iteration":415,"passed_time":0.9435448855,"remaining_time":1.324591858},
{"learn":[4.127068571],"iteration":416,"passed_time":0.9451530119,"remaining_time":1.321400974},
{"learn":[4.125969877],"iteration":417,"passed_time":0.9467374337,"remaining_time":1.318184657},
{"learn":[4.123893633],"iteration":418,"passed_time":0.9483677229,"remaining_time":1.31503973},
{"learn":[4.119643722],"iteration":419,"passed_time":0.9500881729,"remaining_time":1.312026524},
{"learn":[4.11465686],"iteration":420,"passed_time":0.9517064919,"remaining_time":1.308878999},
{"learn":[4.111565986],"iteration":421,"passed_time":0.9533240564,"remaining_time":1.305737689},
{"learn":[4.106322452],"iteration":422,"passed_time":0.9548611211,"remaining_time":1.302493775},
{"learn":[4.104222175],"iteration":423,"passed_time":0.9565548785,"remaining_time":1.299470778},
{"learn":[4.103008002],"iteration":424,"passed_time":0.9580444967,"remaining_time":1.296177848},
{"learn":[4.099176337],"iteration":425,"passed_time":0.9595956455,"remaining_time":1.292976292},
{"learn":[4.096525716],"iteration":426,"passed_time":0.9611707146,"remaining_time":1.289814566},
{"learn":[4.094967724],"iteration":427,"passed_time":0.9627407132,"remaining_time":1.286653476},
{"learn":[4.094683584],"iteration":428,"passed_time":0.9642761907,"remaining_time":1.283453858},
{"learn":[4.091096563],"iteration":429,"passed_time":0.9658384566,"remaining_time":1.280297489},
{"learn":[4.089178677],"iteration":430,"passed_time":0.9674863306,"remaining_time":1.277261536},
{"learn":[4.085335077],"iteration":431,"passed_time":0.9691372499,"remaining_time":1.274236014},
{"learn":[4.084852122],"iteration":432,"passed_time":0.9709719492,"remaining_time":1.271457495},
{"learn":[4.080322952],"iteration":433,"passed_time":0.9727959557,"remaining_time":1.26866938},
{"learn":[4.077449519],"iteration":434,"passed_time":0.97447839,"remaining_time":1.265701817},
{"learn":[4.076568374],"iteration":435,"passed_time":0.9762373347,"remaining_time":1.262839121},
{"learn":[4.076071793],"iteration":436,"passed_time":0.9784553999,"remaining_time":1.260572975},
{"learn":[4.075027644],"iteration":437,"passed_time":0.9829748657,"remaining_time":1.261259988},
{"learn":[4.07020837],"iteration":438,"passed_time":0.9878716702,"remaining_time":1.262405483},
{"learn":[4.06833694],"iteration":439,"passed_time":0.9897976509,"remaining_time":1.259742465},
{"learn":[4.063936568],"iteration":440,"passed_time":0.9924257729,"remaining_time":1.257972805},
{"learn":[4.061734926],"iteration":441,"passed_time":0.9948278568,"remaining_time":1.255913901},
{"learn":[4.060815619],"iteration":442,"passed_time":0.9972671461,"remaining_time":1.253900227},
{"learn":[4.056407489],"iteration":443,"passed_time":1.000687864,"remaining_time":1.253113631},
{"learn":[4.05238936],"iteration":444,"passed_time":1.003089337,"remaining_time":1.251044005},
{"learn":[4.049685254],"iteration":445,"passed_time":1.005368721,"remaining_time":1.248821236},
{"learn":[4.045162016],"iteration":446,"passed_time":1.007823979,"remaining_time":1.246815795},
{"learn":[4.042955482],"iteration":447,"passed_time":1.010488779,"remaining_time":1.245066531},
{"learn":[4.041467663],"iteration":448,"passed_time":1.016174187,"remaining_time":1.247019993},
{"learn":[4.038920476],"iteration":449,"passed_time":1.018565588,"remaining_time":1.244913497},
{"learn":[4.036694383],"iteration":450,"passed_time":1.020989118,"remaining_time":1.242844846},
{"learn":[4.034999007],"iteration":451,"passed_time":1.023465107,"remaining_time":1.240838227},
{"learn":[4.031928018],"iteration":452,"passed_time":1.02596144,"remaining_time":1.238854101},
{"learn":[4.028718143],"iteration":453,"passed_time":1.031239493,"remaining_time":1.240213135},
{"learn":[4.027401978],"iteration":454,"passed_time":1.033052084,"remaining_time":1.237392056},
{"learn":[4.025930598],"iteration":455,"passed_time":1.034872818,"remaining_time":1.234585116},
{"learn":[4.021074523],"iteration":456,"passed_time":1.03673802,"remaining_time":1.231835329},
{"learn":[4.020268486],"iteration":457,"passed_time":1.038447422,"remaining_time":1.228905028},
{"learn":[4.017986361],"iteration":458,"passed_time":1.04021678,"remaining_time":1.226050715},
{"learn":[4.014814804],"iteration":459,"passed_time":1.041952981,"remaining_time":1.223162195},
{"learn":[4.009704796],"iteration":460,"passed_time":1.045433756,"remaining_time":1.222318426},
{"learn":[4.008440457],"iteration":461,"passed_time":1.047535804,"remaining_time":1.219857711},
{"learn":[4.004854849],"iteration":462,"passed_time":1.050182289,"remaining_time":1.218029998},
{"learn":[4.000898028],"iteration":463,"passed_time":1.053338346,"remaining_time":1.2167874},
{"learn":[3.996617985],"iteration":464,"passed_time":1.055533203,"remaining_time":1.214430675},
{"learn":[3.995443319],"iteration":465,"passed_time":1.060608878,"remaining_time":1.215375839},
{"learn":[3.990771995],"iteration":466,"passed_time":1.062790876,"remaining_time":1.212992585},
{"learn":[3.989249359],"iteration":467,"passed_time":1.06478253,"remaining_time":1.210393816},
{"learn":[3.986599538],"iteration":468,"passed_time":1.067607579,"remaining_time":1.208741203},
{"learn":[3.985628919],"iteration":469,"passed_time":1.07022893,"remaining_time":1.206853899},
{"learn":[3.985086112],"iteration":470,"passed_time":1.073071439,"remaining_time":1.205211871},
{"learn":[3.98466839],"iteration":471,"passed_time":1.078219958,"remaining_time":1.206144359},
{"learn":[3.984233894],"iteration":472,"passed_time":1.080590162,"remaining_time":1.203955635},
{"learn":[3.981855845],"iteration":473,"passed_time":1.083246225,"remaining_time":1.202083364},
{"learn":[3.978684264],"iteration":474,"passed_time":1.085863897,"remaining_time":1.20016536},
{"learn":[3.974361269],"iteration":475,"passed_time":1.091590596,"remaining_time":1.201666958},
{"learn":[3.972074049],"iteration":476,"passed_time":1.094276426,"remaining_time":1.199804132},
{"learn":[3.97191982],"iteration":477,"passed_time":1.096805446,"remaining_time":1.197766616},
{"learn":[3.969616848],"iteration":478,"passed_time":1.099336834,"remaining_time":1.195729626},
{"learn":[3.968533527],"iteration":479,"passed_time":1.101976056,"remaining_time":1.193807394},
{"learn":[3.967568753],"iteration":480,"passed_time":1.106739154,"remaining_time":1.194173848},
{"learn":[3.966232553],"iteration":481,"passed_time":1.123381221,"remaining_time":1.207285213},
{"learn":[3.961522393],"iteration":482,"passed_time":1.125947662,"remaining_time":1.205206917},
{"learn":[3.955829553],"iteration":483,"passed_time":1.134785678,"remaining_time":1.20981283},
{"learn":[3.954248095],"iteration":484,"passed_time":1.139772112,"remaining_time":1.210273479},
{"learn":[3.951922606],"iteration":485,"passed_time":1.142734255,"remaining_time":1.208570797},
{"learn":[3.94978202],"iteration":486,"passed_time":1.145082328,"remaining_time":1.206216086},
{"learn":[3.949518999],"iteration":487,"passed_time":1.147439997,"remaining_time":1.203871472},
{"learn":[3.945431216],"iteration":488,"passed_time":1.149851622,"remaining_time":1.201583188},
{"learn":[3.943249086],"iteration":489,"passed_time":1.154676659,"remaining_time":1.201806319},
{"learn":[3.941981548],"iteration":490,"passed_time":1.156837731,"remaining_time":1.199247261},
{"learn":[3.936600517],"iteration":491,"passed_time":1.159086915,"remaining_time":1.196780799},
{"learn":[3.934476885],"iteration":492,"passed_time":1.161262825,"remaining_time":1.194239862},
{"learn":[3.93045798],"iteration":493,"passed_time":1.163432079,"remaining_time":1.191693587},
{"learn":[3.925977375],"iteration":494,"passed_time":1.185039255,"remaining_time":1.208979442},
{"learn":[3.92457993],"iteration":495,"passed_time":1.188738233,"remaining_time":1.20791143},
{"learn":[3.919849146],"iteration":496,"passed_time":1.191206002,"remaining_time":1.205586758},
{"learn":[3.919681964],"iteration":497,"passed_time":1.193882092,"remaining_time":1.203471506},
{"learn":[3.917633027],"iteration":498,"passed_time":1.196587558,"remaining_time":1.2013835},
{"learn":[3.916616419],"iteration":499,"passed_time":1.204390032,"remaining_time":1.204390032},
{"learn":[3.912896166],"iteration":500,"passed_time":1.207957677,"remaining_time":1.20313549},
{"learn":[3.912769674],"iteration":501,"passed_time":1.21066305,"remaining_time":1.201016333},
{"learn":[3.909373788],"iteration":502,"passed_time":1.212966318,"remaining_time":1.198497535},
{"learn":[3.906706036],"iteration":503,"passed_time":1.220553886,"remaining_time":1.201180015},
{"learn":[3.903895664],"iteration":504,"passed_time":1.223799418,"remaining_time":1.199565766},
{"learn":[3.902982967],"iteration":505,"passed_time":1.226878423,"remaining_time":1.197782492},
{"learn":[3.900905528],"iteration":506,"passed_time":1.232088706,"remaining_time":1.198066533},
{"learn":[3.897463465],"iteration":507,"passed_time":1.234231143,"remaining_time":1.195357721},
{"learn":[3.895918033],"iteration":508,"passed_time":1.242338345,"remaining_time":1.198404965},
{"learn":[3.893921936],"iteration":509,"passed_time":1.248449545,"remaining_time":1.199490739},
{"learn":[3.890237934],"iteration":510,"passed_time":1.250784326,"remaining_time":1.196934512},
{"learn":[3.887311613],"iteration":511,"passed_time":1.253698985,"remaining_time":1.194931845},
{"learn":[3.884869735],"iteration":512,"passed_time":1.257736993,"remaining_time":1.193992038},
{"learn":[3.882101231],"iteration":513,"passed_time":1.261507159,"remaining_time":1.192786925},
{"learn":[3.88060368],"iteration":514,"passed_time":1.263843131,"remaining_time":1.190221201},
{"learn":[3.877726076],"iteration":515,"passed_time":1.266362847,"remaining_time":1.187828717},
{"learn":[3.874938145],"iteration":516,"passed_time":1.268903672,"remaining_time":1.185455461},
{"learn":[3.874340833],"iteration":517,"passed_time":1.270949603,"remaining_time":1.182621059},
{"learn":[3.873105224],"iteration":518,"passed_time":1.27287649,"remaining_time":1.179679368},
{"learn":[3.869800236],"iteration":519,"passed_time":1.278058624,"remaining_time":1.179746422},
{"learn":[3.867932518],"iteration":520,"passed_time":1.280508827,"remaining_time":1.177281628},
{"learn":[3.866666962],"iteration":521,"passed_time":1.283198339,"remaining_time":1.175036027},
{"learn":[3.865527652],"iteration":522,"passed_time":1.285319098,"remaining_time":1.17227},
{"learn":[3.861900081],"iteration":523,"passed_time":1.288133517,"remaining_time":1.170136554},
{"learn":[3.858502887],"iteration":524,"passed_time":1.293391217,"remaining_time":1.170211101},
{"learn":[3.858335097],"iteration":525,"passed_time":1.29613932,"remaining_time":1.168003874},
{"learn":[3.855719306],"iteration":526,"passed_time":1.298464927,"remaining_time":1.16541539},
{"learn":[3.855137428],"iteration":527,"passed_time":1.300500069,"remaining_time":1.162568244},
{"learn":[3.851985706],"iteration":528,"passed_time":1.303190374,"remaining_time":1.160307498},
{"learn":[3.851051809],"iteration":529,"passed_time":1.308045924,"remaining_time":1.159965254},
{"learn":[3.850679146],"iteration":530,"passed_time":1.310971965,"remaining_time":1.157901792},
{"learn":[3.848179484],"iteration":531,"passed_time":1.313205113,"remaining_time":1.15522555},
{"learn":[3.844551071],"iteration":532,"passed_time":1.315398122,"remaining_time":1.152515803},
{"learn":[3.841604794],"iteration":533,"passed_time":1.317368401,"remaining_time":1.149613623},
{"learn":[3.83969656],"iteration":534,"passed_time":1.319600969,"remaining_time":1.146942898},
{"learn":[3.836811463],"iteration":535,"passed_time":1.324019096,"remaining_time":1.146165785},
{"learn":[3.834182551],"iteration":536,"passed_time":1.326123473,"remaining_time":1.143380201},
{"learn":[3.828012842],"iteration":537,"passed_time":1.328164124,"remaining_time":1.140542426},
{"learn":[3.826636176],"iteration":538,"passed_time":1.330004887,"remaining_time":1.137536647},
{"learn":[3.826189798],"iteration":539,"passed_time":1.332031973,"remaining_time":1.134693903},
{"learn":[3.824104738],"iteration":540,"passed_time":1.333878346,"remaining_time":1.131700852},
{"learn":[3.82300218],"iteration":541,"passed_time":1.340152147,"remaining_time":1.13245329},
{"learn":[3.817146402],"iteration":542,"passed_time":1.343410612,"remaining_time":1.130642081},
{"learn":[3.814638044],"iteration":543,"passed_time":1.345756974,"remaining_time":1.128060993},
{"learn":[3.812979573],"iteration":544,"passed_time":1.347810154,"remaining_time":1.125236},
{"learn":[3.811938825],"iteration":545,"passed_time":1.349846941,"remaining_time":1.122400204},
{"learn":[3.811479418],"iteration":546,"passed_time":1.354866237,"remaining_time":1.122037304},
{"learn":[3.80742981],"iteration":547,"passed_time":1.356795385,"remaining_time":1.119108602},
{"learn":[3.805097043],"iteration":548,"passed_time":1.358798442,"remaining_time":1.116244257},
{"learn":[3.801577232],"iteration":549,"passed_time":1.361018898,"remaining_time":1.113560917},
{"learn":[3.799762083],"iteration":550,"passed_time":1.36310854,"remaining_time":1.110772657},
{"learn":[3.796393455],"iteration":551,"passed_time":1.365312222,"remaining_time":1.108079485},
{"learn":[3.793486459],"iteration":552,"passed_time":1.368117559,"remaining_time":1.105874411},
{"learn":[3.792006091],"iteration":553,"passed_time":1.370097046,"remaining_time":1.103002315},
{"learn":[3.78932128],"iteration":554,"passed_time":1.372151877,"remaining_time":1.100193847},
{"learn":[3.787581812],"iteration":555,"passed_time":1.374158682,"remaining_time":1.097349739},
{"learn":[3.785308865],"iteration":556,"passed_time":1.376148626,"remaining_time":1.094495227},
{"learn":[3.78465475],"iteration":557,"passed_time":1.378238196,"remaining_time":1.091722729},
{"learn":[3.780498869],"iteration":558,"passed_time":1.383146949,"remaining_time":1.091176752},
{"learn":[3.778734909],"iteration":559,"passed_time":1.385388269,"remaining_time":1.088519355},
{"learn":[3.778652349],"iteration":560,"passed_time":1.387431158,"remaining_time":1.085708161},
{"learn":[3.777928006],"iteration":561,"passed_time":1.389316954,"remaining_time":1.08277727},
{"learn":[3.776131406],"iteration":562,"passed_time":1.391685463,"remaining_time":1.080224773},
{"learn":[3.772925617],"iteration":563,"passed_time":1.393829243,"remaining_time":1.077499202},
{"learn":[3.7727745],"iteration":564,"passed_time":1.397935471,"remaining_time":1.076286602},
{"learn":[3.771763073],"iteration":565,"passed_time":1.399843688,"remaining_time":1.073378376},
{"learn":[3.768738162],"iteration":566,"passed_time":1.402111131,"remaining_time":1.070748006},
{"learn":[3.767220794],"iteration":567,"passed_time":1.404254929,"remaining_time":1.068024876},
{"learn":[3.766691102],"iteration":568,"passed_time":1.406080366,"remaining_time":1.065062632},
{"learn":[3.766259335],"iteration":569,"passed_time":1.40778472,"remaining_time":1.062013034},
{"learn":[3.76116362],"iteration":570,"passed_time":1.411966144,"remaining_time":1.060829205},
{"learn":[3.758633056],"iteration":571,"passed_time":1.414353464,"remaining_time":1.058292452},
{"learn":[3.754603809],"iteration":572,"passed_time":1.416421643,"remaining_time":1.055518397},
{"learn":[3.754070549],"iteration":573,"passed_time":1.418385568,"remaining_time":1.052669428},
{"learn":[3.750534319],"iteration":574,"passed_time":1.420548433,"remaining_time":1.049970581},
{"learn":[3.746491516],"iteration":575,"passed_time":1.422552067,"remaining_time":1.047156383},
{"learn":[3.744210544],"iteration":576,"passed_time":1.426389543,"remaining_time":1.045689388},
{"learn":[3.742929991],"iteration":577,"passed_time":1.428902353,"remaining_time":1.043247046},
{"learn":[3.740402992],"iteration":578,"passed_time":1.430921352,"remaining_time":1.040445404},
{"learn":[3.739644243],"iteration":579,"passed_time":1.432796673,"remaining_time":1.037542418},
{"learn":[3.737529404],"iteration":580,"passed_time":1.434808554,"remaining_time":1.034741453},
{"learn":[3.737196923],"iteration":581,"passed_time":1.436753386,"remaining_time":1.031895044},
{"learn":[3.733954464],"iteration":582,"passed_time":1.438847793,"remaining_time":1.029158713},
{"learn":[3.731608623],"iteration":583,"passed_time":1.44344765,"remaining_time":1.028209285},
{"learn":[3.729843952],"iteration":584,"passed_time":1.445757671,"remaining_time":1.025622963},
{"learn":[3.727223798],"iteration":585,"passed_time":1.447981545,"remaining_time":1.022976723},
{"learn":[3.725351667],"iteration":586,"passed_time":1.450142672,"remaining_time":1.020287774},
{"learn":[3.725026912],"iteration":587,"passed_time":1.452301999,"remaining_time":1.01759936},
{"learn":[3.721974565],"iteration":588,"passed_time":1.454542528,"remaining_time":1.014969404},
{"learn":[3.720269493],"iteration":589,"passed_time":1.457436345,"remaining_time":1.012794748},
{"learn":[3.718907466],"iteration":590,"passed_time":1.45947434,"remaining_time":1.010025389},
{"learn":[3.715602912],"iteration":591,"passed_time":1.461490446,"remaining_time":1.007243416},
{"learn":[3.714463059],"iteration":592,"passed_time":1.463760508,"remaining_time":1.004638325},
{"learn":[3.710802077],"iteration":593,"passed_time":1.466272245,"remaining_time":1.002199548},
{"learn":[3.708032435],"iteration":594,"passed_time":1.470723422,"remaining_time":1.001080649},
{"learn":[3.703788939],"iteration":595,"passed_time":1.472585458,"remaining_time":0.9981955121},
{"learn":[3.702500944],"iteration":596,"passed_time":1.47479368,"remaining_time":0.9955474925},
{"learn":[3.698196925],"iteration":597,"passed_time":1.476843107,"remaining_time":0.9927941955},
{"learn":[3.69658891],"iteration":598,"passed_time":1.478983778,"remaining_time":0.9901043324},
{"learn":[3.696124066],"iteration":599,"passed_time":1.480930068,"remaining_time":0.987286712},
{"learn":[3.693537052],"iteration":600,"passed_time":1.484742821,"remaining_time":0.9857111241},
{"learn":[3.691343275],"iteration":601,"passed_time":1.486993907,"remaining_time":0.9830956395},
{"learn":[3.690973831],"iteration":602,"passed_time":1.48867876,"remaining_time":0.9801085697},
{"learn":[3.686151073],"iteration":603,"passed_time":1.490710523,"remaining_time":0.977353257},
{"learn":[3.683921982],"iteration":604,"passed_time":1.492977439,"remaining_time":0.9747538649},
{"learn":[3.679975271],"iteration":605,"passed_time":1.494946609,"remaining_time":0.9719619865},
{"learn":[3.674047638],"iteration":606,"passed_time":1.496948815,"remaining_time":0.9691942084},
{"learn":[3.673151794],"iteration":607,"passed_time":1.501528999,"remaining_time":0.9680910653},
{"learn":[3.670953108],"iteration":608,"passed_time":1.503371211,"remaining_time":0.9652186266},
{"learn":[3.6703947],"iteration":609,"passed_time":1.505261846,"remaining_time":0.9623805244},
{"learn":[3.668433805],"iteration":610,"passed_time":1.507152672,"remaining_time":0.9595456458},
{"learn":[3.668304956],"iteration":611,"passed_time":1.509101878,"remaining_time":0.9567508638},
{"learn":[3.667880012],"iteration":612,"passed_time":1.511265566,"remaining_time":0.9540942481},
{"learn":[3.667282264],"iteration":613,"passed_time":1.515181457,"remaining_time":0.9525407855},
{"learn":[3.664611483],"iteration":614,"passed_time":1.517630687,"remaining_time":0.9500614872},
{"learn":[3.662543394],"iteration":615,"passed_time":1.519729006,"remaining_time":0.9473635361},
{"learn":[3.659041959],"iteration":616,"passed_time":1.521586335,"remaining_time":0.9445179357},
{"learn":[3.656868545],"iteration":617,"passed_time":1.523506722,"remaining_time":0.9417145112},
{"learn":[3.654785614],"iteration":618,"passed_time":1.525265024,"remaining_time":0.9388141749},
{"learn":[3.654566096],"iteration":619,"passed_time":1.527023454,"remaining_time":0.9359176008},
{"learn":[3.651007045],"iteration":620,"passed_time":1.530375328,"remaining_time":0.9339971811},
{"learn":[3.648921786],"iteration":621,"passed_time":1.53263109,"remaining_time":0.931406032},
{"learn":[3.647655706],"iteration":622,"passed_time":1.534345858,"remaining_time":0.9284885853},
{"learn":[3.647241144],"iteration":623,"passed_time":1.536033062,"remaining_time":0.9255583837},
{"learn":[3.644195689],"iteration":624,"passed_time":1.53798929,"remaining_time":0.9227935739},
{"learn":[3.642632246],"iteration":625,"passed_time":1.539807031,"remaining_time":0.9199486094},
{"learn":[3.642523322],"iteration":626,"passed_time":1.541305843,"remaining_time":0.9169171922},
{"learn":[3.641494659],"iteration":627,"passed_time":1.543357392,"remaining_time":0.9142180729},
{"learn":[3.63976496],"iteration":628,"passed_time":1.546503441,"remaining_time":0.9121665765},
{"learn":[3.637945652],"iteration":629,"passed_time":1.548251483,"remaining_time":0.9092905534},
{"learn":[3.636233667],"iteration":630,"passed_time":1.549942544,"remaining_time":0.9063847841},
{"learn":[3.635304404],"iteration":631,"passed_time":1.551653276,"remaining_time":0.9034943127},
{"learn":[3.632234951],"iteration":632,"passed_time":1.553457603,"remaining_time":0.9006618333},
{"learn":[3.631630987],"iteration":633,"passed_time":1.555234013,"remaining_time":0.897816481},
{"learn":[3.630301009],"iteration":634,"passed_time":1.557210704,"remaining_time":0.8950896175},
{"learn":[3.629077964],"iteration":635,"passed_time":1.560531577,"remaining_time":0.8931344246},
{"learn":[3.628004522],"iteration":636,"passed_time":1.562449431,"remaining_time":0.8903754216},
{"learn":[3.625062876],"iteration":637,"passed_time":1.564197308,"remaining_time":0.8875226102},
{"learn":[3.624917986],"iteration":638,"passed_time":1.565835622,"remaining_time":0.884611361},
{"learn":[3.622887087],"iteration":639,"passed_time":1.567492254,"remaining_time":0.8817143927},
{"learn":[3.621220865],"iteration":640,"passed_time":1.569501107,"remaining_time":0.879018561},
{"learn":[3.621143844],"iteration":641,"passed_time":1.576147277,"remaining_time":0.8789107869},
{"learn":[3.620822821],"iteration":642,"passed_time":1.580760621,"remaining_time":0.8776540308},
{"learn":[3.619202826],"iteration":643,"passed_time":1.585002078,"remaining_time":0.8761812731},
{"learn":[3.618204882],"iteration":644,"passed_time":1.586782834,"remaining_time":0.8733455911},
{"learn":[3.614259666],"iteration":645,"passed_time":1.590130429,"remaining_time":0.8713717828},
{"learn":[3.613415661],"iteration":646,"passed_time":1.592253653,"remaining_time":0.8687257178},
{"learn":[3.611096773],"iteration":647,"passed_time":1.594072155,"remaining_time":0.8659157385},
{"learn":[3.610820695],"iteration":648,"passed_time":1.595818084,"remaining_time":0.8630695648},
{"learn":[3.609290065],"iteration":649,"passed_time":1.597685229,"remaining_time":0.8602920462},
{"learn":[3.60897947],"iteration":650,"passed_time":1.59949471,"remaining_time":0.8574864112},
{"learn":[3.606570702],"iteration":651,"passed_time":1.601290039,"remaining_time":0.8546762786},
{"learn":[3.606292637],"iteration":652,"passed_time":1.604296304,"remaining_time":0.8525127374},
{"learn":[3.602753838],"iteration":653,"passed_time":1.607054057,"remaining_time":0.8502151431},
{"learn":[3.599755869],"iteration":654,"passed_time":1.60899695,"remaining_time":0.847486943},
{"learn":[3.599509575],"iteration":655,"passed_time":1.610707859,"remaining_time":0.8446394872},
{"learn":[3.595337722],"iteration":656,"passed_time":1.612498543,"remaining_time":0.8418371388},
{"learn":[3.595168561],"iteration":657,"passed_time":1.614225186,"remaining_time":0.8390045801},
{"learn":[3.59290559],"iteration":658,"passed_time":1.616006807,"remaining_time":0.8362038257},
{"learn":[3.592015928],"iteration":659,"passed_time":1.618688166,"remaining_time":0.8338696615},
{"learn":[3.590680403],"iteration":660,"passed_time":1.621200717,"remaining_time":0.8314478716},
{"learn":[3.590361532],"iteration":661,"passed_time":1.622846104,"remaining_time":0.8285830559},
{"learn":[3.589069739],"iteration":662,"passed_time":1.624600951,"remaining_time":0.8257775575},
{"learn":[3.585010186],"iteration":663,"passed_time":1.626292035,"remaining_time":0.8229429574},
{"learn":[3.582997552],"iteration":664,"passed_time":1.628093509,"remaining_time":0.820167407},
{"learn":[3.582119256],"iteration":665,"passed_time":1.629825867,"remaining_time":0.8173601196},
{"learn":[3.579019356],"iteration":666,"passed_time":1.631526676,"remaining_time":0.8145403044},
{"learn":[3.57719559],"iteration":667,"passed_time":1.635284371,"remaining_time":0.8127461248},
{"learn":[3.574050046],"iteration":668,"passed_time":1.637207872,"remaining_time":0.8100385735},
{"learn":[3.572204518],"iteration":669,"passed_time":1.638935522,"remaining_time":0.8072368987},
{"learn":[3.569508025],"iteration":670,"passed_time":1.640586592,"remaining_time":0.8044008772},
{"learn":[3.566268704],"iteration":671,"passed_time":1.642445578,"remaining_time":0.8016698655},
{"learn":[3.562564052],"iteration":672,"passed_time":1.644330729,"remaining_time":0.7989541579},
{"learn":[3.561173586],"iteration":673,"passed_time":1.646186401,"remaining_time":0.7962266568},
{"learn":[3.559551904],"iteration":674,"passed_time":1.649799747,"remaining_time":0.7943480265},
{"learn":[3.558593054],"iteration":675,"passed_time":1.651800245,"remaining_time":0.7916912416},
{"learn":[3.555647008],"iteration":676,"passed_time":1.653629303,"remaining_time":0.7889546012},
{"learn":[3.553100059],"iteration":677,"passed_time":1.655413567,"remaining_time":0.7861993638},
{"learn":[3.55085578],"iteration":678,"passed_time":1.657262568,"remaining_time":0.7834775908},
{"learn":[3.550737965],"iteration":679,"passed_time":1.65890879,"remaining_time":0.7806629601},
{"learn":[3.549408772],"iteration":680,"passed_time":1.660676753,"remaining_time":0.7779087873},
{"learn":[3.547390589],"iteration":681,"passed_time":1.663796441,"remaining_time":0.7757877831},
{"learn":[3.54723575],"iteration":682,"passed_time":1.666363913,"remaining_time":0.7734075554},
{"learn":[3.543988891],"iteration":683,"passed_time":1.668163077,"remaining_time":0.7706718308},
{"learn":[3.543868508],"iteration":684,"passed_time":1.669859757,"remaining_time":0.767891713},
{"learn":[3.542752124],"iteration":685,"passed_time":1.671531491,"remaining_time":0.7651033357},
{"learn":[3.541334315],"iteration":686,"passed_time":1.673368203,"remaining_time":0.7623933733},
{"learn":[3.540208266],"iteration":687,"passed_time":1.675126611,"remaining_time":0.7596504401},
{"learn":[3.537730983],"iteration":688,"passed_time":1.677475562,"remaining_time":0.757176923},
{"learn":[3.53419867],"iteration":689,"passed_time":1.680304992,"remaining_time":0.7549196343},
{"learn":[3.532628335],"iteration":690,"passed_time":1.682118486,"remaining_time":0.7522063852},
{"learn":[3.532204987],"iteration":691,"passed_time":1.683961037,"remaining_time":0.7495086695},
{"learn":[3.530618147],"iteration":692,"passed_time":1.685840375,"remaining_time":0.7468297188},
{"learn":[3.528909306],"iteration":693,"passed_time":1.687718404,"remaining_time":0.744152495},
{"learn":[3.526700678],"iteration":694,"passed_time":1.689483976,"remaining_time":0.7414282196},
{"learn":[3.526439574],"iteration":695,"passed_time":1.691330941,"remaining_time":0.73874225},
{"learn":[3.525784216],"iteration":696,"passed_time":1.694569808,"remaining_time":0.7366637758},
{"learn":[3.524112693],"iteration":697,"passed_time":1.696757537,"remaining_time":0.7341271867},
{"learn":[3.522813541],"iteration":698,"passed_time":1.698624646,"remaining_time":0.7314535313},
{"learn":[3.519148203],"iteration":699,"passed_time":1.700441424,"remaining_time":0.7287606103},
{"learn":[3.517236747],"iteration":700,"passed_time":1.702033996,"remaining_time":0.7259745574},
{"learn":[3.515603888],"iteration":701,"passed_time":1.703816752,"remaining_time":0.7232726384},
{"learn":[3.51263524],"iteration":702,"passed_time":1.70566652,"remaining_time":0.7206016451},
{"learn":[3.51123442],"iteration":703,"passed_time":1.709601521,"remaining_time":0.7188097303},
{"learn":[3.50828027],"iteration":704,"passed_time":1.711362724,"remaining_time":0.7161021329},
{"learn":[3.508265537],"iteration":705,"passed_time":1.712483832,"remaining_time":0.7131306607},
{"learn":[3.506774876],"iteration":706,"passed_time":1.716102069,"remaining_time":0.7111993014},
{"learn":[3.50552068],"iteration":707,"passed_time":1.718243463,"remaining_time":0.7086540836},
{"learn":[3.501973993],"iteration":708,"passed_time":1.720140537,"remaining_time":0.7060097266},
{"learn":[3.498880354],"iteration":709,"passed_time":1.722365579,"remaining_time":0.7035014337},
{"learn":[3.497370959],"iteration":710,"passed_time":1.724722325,"remaining_time":0.701047471},
{"learn":[3.496050455],"iteration":711,"passed_time":1.726453453,"remaining_time":0.6983407225},
{"learn":[3.495630067],"iteration":712,"passed_time":1.728241443,"remaining_time":0.6956595992},
{"learn":[3.49550669],"iteration":713,"passed_time":1.729935655,"remaining_time":0.6929434135},
{"learn":[3.493652375],"iteration":714,"passed_time":1.731660899,"remaining_time":0.6902424562},
{"learn":[3.491915684],"iteration":715,"passed_time":1.733463957,"remaining_time":0.6875750891},
{"learn":[3.490303956],"iteration":716,"passed_time":1.735178101,"remaining_time":0.6848750384},
{"learn":[3.488363853],"iteration":717,"passed_time":1.737524678,"remaining_time":0.6824261271},
{"learn":[3.485483936],"iteration":718,"passed_time":1.739375842,"remaining_time":0.6797838825},
{"learn":[3.483763466],"iteration":719,"passed_time":1.74112247,"remaining_time":0.6771031827},
{"learn":[3.481642352],"iteration":720,"passed_time":1.742756886,"remaining_time":0.6743816522},
{"learn":[3.479826119],"iteration":721,"passed_time":1.744576219,"remaining_time":0.6717343338},
{"learn":[3.478588728],"iteration":722,"passed_time":1.74621704,"remaining_time":0.6690209131},
{"learn":[3.475390887],"iteration":723,"passed_time":1.747868756,"remaining_time":0.6663146087},
{"learn":[3.472636852],"iteration":724,"passed_time":1.749563478,"remaining_time":0.663627526},
{"learn":[3.47061883],"iteration":725,"passed_time":1.751378305,"remaining_time":0.6609885062},
{"learn":[3.46953149],"iteration":726,"passed_time":1.753162277,"remaining_time":0.6583401673},
{"learn":[3.467217162],"iteration":727,"passed_time":1.754897108,"remaining_time":0.6556758427},
{"learn":[3.465686216],"iteration":728,"passed_time":1.756625431,"remaining_time":0.6530116486},
{"learn":[3.462631216],"iteration":729,"passed_time":1.758430659,"remaining_time":0.6503784628},
{"learn":[3.461451053],"iteration":730,"passed_time":1.760128274,"remaining_time":0.6477079423},
{"learn":[3.458950469],"iteration":731,"passed_time":1.761860187,"remaining_time":0.6450526366},
{"learn":[3.458072145],"iteration":732,"passed_time":1.763491752,"remaining_time":0.6423632986},
{"learn":[3.454364268],"iteration":733,"passed_time":1.765184513,"remaining_time":0.6396990198},
{"learn":[3.453243406],"iteration":734,"passed_time":1.766992784,"remaining_time":0.6370790311},
{"learn":[3.453017963],"iteration":735,"passed_time":1.768760512,"remaining_time":0.6344467054},
{"learn":[3.45201581],"iteration":736,"passed_time":1.770401317,"remaining_time":0.6317714332},
{"learn":[3.449510107],"iteration":737,"passed_time":1.772118124,"remaining_time":0.6291259466},
{"learn":[3.447189189],"iteration":738,"passed_time":1.773858642,"remaining_time":0.6264913471},
{"learn":[3.446423605],"iteration":739,"passed_time":1.77545736,"remaining_time":0.6238093428},
{"learn":[3.445531987],"iteration":740,"passed_time":1.777000429,"remaining_time":0.621110811},
{"learn":[3.445328199],"iteration":741,"passed_time":1.778791099,"remaining_time":0.6185014874},
{"learn":[3.443327544],"iteration":742,"passed_time":1.780597571,"remaining_time":0.6158998329},
{"learn":[3.441475798],"iteration":743,"passed_time":1.78254263,"remaining_time":0.6133480018},
{"learn":[3.439046501],"iteration":744,"passed_time":1.78455335,"remaining_time":0.6108202741},
{"learn":[3.435899469],"iteration":745,"passed_time":1.786826287,"remaining_time":0.6083832129},
{"learn":[3.433988352],"iteration":746,"passed_time":1.789130718,"remaining_time":0.6059572579},
{"learn":[3.433413263],"iteration":747,"passed_time":1.791312725,"remaining_time":0.6034903832},
{"learn":[3.429944699],"iteration":748,"passed_time":1.793225469,"remaining_time":0.6009340356},
{"learn":[3.429291634],"iteration":749,"passed_time":1.794989983,"remaining_time":0.5983299943},
{"learn":[3.429175603],"iteration":750,"passed_time":1.796916089,"remaining_time":0.595781766},
{"learn":[3.428780323],"iteration":751,"passed_time":1.798711289,"remaining_time":0.593192021},
{"learn":[3.423893341],"iteration":752,"passed_time":1.800373796,"remaining_time":0.5905608602},
{"learn":[3.421024316],"iteration":753,"passed_time":1.802106716,"remaining_time":0.5879552416},
{"learn":[3.420969872],"iteration":754,"passed_time":1.803733879,"remaining_time":0.5853176165},
{"learn":[3.419544785],"iteration":755,"passed_time":1.805415511,"remaining_time":0.5827002442},
{"learn":[3.417057977],"iteration":756,"passed_time":1.807151152,"remaining_time":0.5801026817},
{"learn":[3.415160245],"iteration":757,"passed_time":1.80880806,"remaining_time":0.5774822567},
{"learn":[3.412854597],"iteration":758,"passed_time":1.810775246,"remaining_time":0.574962891},
{"learn":[3.410926347],"iteration":759,"passed_time":1.812797138,"remaining_time":0.572462254},
{"learn":[3.408963843],"iteration":760,"passed_time":1.815012808,"remaining_time":0.5700237335},
{"learn":[3.407629634],"iteration":761,"passed_time":1.817062528,"remaining_time":0.5675339653},
{"learn":[3.404384724],"iteration":762,"passed_time":1.818929879,"remaining_time":0.5649887042},
{"learn":[3.403041656],"iteration":763,"passed_time":1.820688448,"remaining_time":0.5624116149},
{"learn":[3.401101731],"iteration":764,"passed_time":1.822492593,"remaining_time":0.5598506658},
{"learn":[3.400890668],"iteration":765,"passed_time":1.824152584,"remaining_time":0.5572476562},
{"learn":[3.399289941],"iteration":766,"passed_time":1.825817061,"remaining_time":0.5546484683},
{"learn":[3.399202366],"iteration":767,"passed_time":1.827451833,"remaining_time":0.5520427413},
{"learn":[3.397447845],"iteration":768,"passed_time":1.829208265,"remaining_time":0.5494760849},
{"learn":[3.394655341],"iteration":769,"passed_time":1.831305052,"remaining_time":0.5470131974},
{"learn":[3.393228229],"iteration":770,"passed_time":1.833083308,"remaining_time":0.5444566506},
{"learn":[3.389691197],"iteration":771,"passed_time":1.834861062,"remaining_time":0.5419019717},
{"learn":[3.389626772],"iteration":772,"passed_time":1.836461422,"remaining_time":0.5392972093},
{"learn":[3.388480222],"iteration":773,"passed_time":1.838149335,"remaining_time":0.5367206069},
{"learn":[3.388215066],"iteration":774,"passed_time":1.839857143,"remaining_time":0.5341520737},
{"learn":[3.386324358],"iteration":775,"passed_time":1.841613977,"remaining_time":0.5315999109},
{"learn":[3.383913061],"iteration":776,"passed_time":1.843483622,"remaining_time":0.5290821721},
{"learn":[3.382839768],"iteration":777,"passed_time":1.845470131,"remaining_time":0.5265994462},
{"learn":[3.381961844],"iteration":778,"passed_time":1.847236493,"remaining_time":0.5240555392},
{"learn":[3.381521703],"iteration":779,"passed_time":1.84915619,"remaining_time":0.5215568742},
{"learn":[3.380918963],"iteration":780,"passed_time":1.85088263,"remaining_time":0.5190055005},
{"learn":[3.377139006],"iteration":781,"passed_time":1.852702806,"remaining_time":0.516482368},
{"learn":[3.376004372],"iteration":782,"passed_time":1.854548762,"remaining_time":0.5139681754},
{"learn":[3.373826468],"iteration":783,"passed_time":1.856395375,"remaining_time":0.5114558686},
{"learn":[3.373546786],"iteration":784,"passed_time":1.858103304,"remaining_time":0.5089072743},
{"learn":[3.372109181],"iteration":785,"passed_time":1.859762558,"remaining_time":0.5063475667},
{"learn":[3.370764924],"iteration":786,"passed_time":1.861440138,"remaining_time":0.5037951071},
{"learn":[3.367833107],"iteration":787,"passed_time":1.863539513,"remaining_time":0.5013583461},
{"learn":[3.36450404],"iteration":788,"passed_time":1.865399476,"remaining_time":0.498858415},
{"learn":[3.361794558],"iteration":789,"passed_time":1.867170898,"remaining_time":0.4963365678},
{"learn":[3.356880529],"iteration":790,"passed_time":1.86887887,"remaining_time":0.4937998532},
{"learn":[3.353843509],"iteration":791,"passed_time":1.870558379,"remaining_time":0.4912577561},
{"learn":[3.353640253],"iteration":792,"passed_time":1.872215144,"remaining_time":0.4887118975},
{"learn":[3.353055088],"iteration":793,"passed_time":1.873819332,"remaining_time":0.4861546379},
{"learn":[3.351415617],"iteration":794,"passed_time":1.875607225,"remaining_time":0.4836471462},
{"learn":[3.349169061],"iteration":795,"passed_time":1.877291848,"remaining_time":0.4811149963},
{"learn":[3.346211014],"iteration":796,"passed_time":1.87906797,"remaining_time":0.4786082785},
{"learn":[3.344560452],"iteration":797,"passed_time":1.880920031,"remaining_time":0.4761226144},
{"learn":[3.344445461],"iteration":798,"passed_time":1.882987464,"remaining_time":0.4736927163},
{"learn":[3.342608898],"iteration":799,"passed_time":1.884815396,"remaining_time":0.4712038491},
{"learn":[3.339572899],"iteration":800,"passed_time":1.886626394,"remaining_time":0.4687124249},
{"learn":[3.339309302],"iteration":801,"passed_time":1.888223832,"remaining_time":0.4661699736},
{"learn":[3.33698088],"iteration":802,"passed_time":1.890179963,"remaining_time":0.4637178739},
{"learn":[3.334746342],"iteration":803,"passed_time":1.892086865,"remaining_time":0.4612550069},
{"learn":[3.332048511],"iteration":804,"passed_time":1.893814518,"remaining_time":0.4587501006},
{"learn":[3.331932544],"iteration":805,"passed_time":1.895309024,"remaining_time":0.4561910058},
{"learn":[3.330541133],"iteration":806,"passed_time":1.897681429,"remaining_time":0.4538445053},
{"learn":[3.329124989],"iteration":807,"passed_time":1.899711422,"remaining_time":0.4514165756},
{"learn":[3.32583918],"iteration":808,"passed_time":1.901527939,"remaining_time":0.4489392291},
{"learn":[3.325287299],"iteration":809,"passed_time":1.903981156,"remaining_time":0.4466128638},
{"learn":[3.322745162],"iteration":810,"passed_time":1.907535679,"remaining_time":0.4445428402},
{"learn":[3.319733662],"iteration":811,"passed_time":1.910424842,"remaining_time":0.4423151111},
{"learn":[3.318080007],"iteration":812,"passed_time":1.91334582,"remaining_time":0.4400930729},
{"learn":[3.317179538],"iteration":813,"passed_time":1.916256864,"remaining_time":0.4378670475},
{"learn":[3.315685949],"iteration":814,"passed_time":1.918813594,"remaining_time":0.435558914},
{"learn":[3.314944576],"iteration":815,"passed_time":1.921073428,"remaining_time":0.433183224},
{"learn":[3.312369052],"iteration":816,"passed_time":1.923425045,"remaining_time":0.430828376},
{"learn":[3.312321621],"iteration":817,"passed_time":1.925155766,"remaining_time":0.4283353905},
{"learn":[3.309465776],"iteration":818,"passed_time":1.927531905,"remaining_time":0.4259869045},
{"learn":[3.308307377],"iteration":819,"passed_time":1.929731301,"remaining_time":0.4235995538},
{"learn":[3.308076804],"iteration":820,"passed_time":1.93187617,"remaining_time":0.4212007727},
{"learn":[3.305643326],"iteration":821,"passed_time":1.934098143,"remaining_time":0.4188193059},
{"learn":[3.304154814],"iteration":822,"passed_time":1.936742911,"remaining_time":0.4165291559},
{"learn":[3.303076321],"iteration":823,"passed_time":1.938974461,"remaining_time":0.4141498848},
{"learn":[3.301746372],"iteration":824,"passed_time":1.941201356,"remaining_time":0.4117699846},
{"learn":[3.301345455],"iteration":825,"passed_time":1.943464485,"remaining_time":0.4093980877},
{"learn":[3.299181039],"iteration":826,"passed_time":1.945657661,"remaining_time":0.4070118202},
{"learn":[3.297989357],"iteration":827,"passed_time":1.947962995,"remaining_time":0.4046493177},
{"learn":[3.294775182],"iteration":828,"passed_time":1.950264201,"remaining_time":0.4022861018},
{"learn":[3.293840636],"iteration":829,"passed_time":1.952532969,"remaining_time":0.3999163913},
{"learn":[3.289279397],"iteration":830,"passed_time":1.95477445,"remaining_time":0.3975413744},
{"learn":[3.286204979],"iteration":831,"passed_time":1.957048472,"remaining_time":0.3951732492},
{"learn":[3.284833593],"iteration":832,"passed_time":1.959233924,"remaining_time":0.3927875934},
{"learn":[3.283519914],"iteration":833,"passed_time":1.961207589,"remaining_time":0.3903602636},
{"learn":[3.282853026],"iteration":834,"passed_time":1.963149629,"remaining_time":0.3879277709},
{"learn":[3.281944673],"iteration":835,"passed_time":1.965259572,"remaining_time":0.3855293897},
{"learn":[3.279764865],"iteration":836,"passed_time":1.966958526,"remaining_time":0.3830516603},
{"learn":[3.277468839],"iteration":837,"passed_time":1.968582708,"remaining_time":0.380561335},
{"learn":[3.277124974],"iteration":838,"passed_time":1.97031877,"remaining_time":0.3780945434},
{"learn":[3.275636037],"iteration":839,"passed_time":1.972414809,"remaining_time":0.3756980588},
{"learn":[3.274413635],"iteration":840,"passed_time":1.974214136,"remaining_time":0.3732461922},
{"learn":[3.272636087],"iteration":841,"passed_time":1.975969963,"remaining_time":0.3707877127},
{"learn":[3.269644466],"iteration":842,"passed_time":1.977831635,"remaining_time":0.368350613},
{"learn":[3.26852083],"iteration":843,"passed_time":1.97974106,"remaining_time":0.3659237031},
{"learn":[3.267820927],"iteration":844,"passed_time":1.981764014,"remaining_time":0.3635188428},
{"learn":[3.267331099],"iteration":845,"passed_time":1.983474161,"remaining_time":0.3610579442},
{"learn":[3.267231014],"iteration":846,"passed_time":1.985174026,"remaining_time":0.358596961},
{"learn":[3.267158695],"iteration":847,"passed_time":1.986861914,"remaining_time":0.3561356261},
{"learn":[3.264718705],"iteration":848,"passed_time":1.988764216,"remaining_time":0.3537142481},
{"learn":[3.261678512],"iteration":849,"passed_time":1.990720686,"remaining_time":0.3513036504},
{"learn":[3.261368381],"iteration":850,"passed_time":1.992375013,"remaining_time":0.3488412184},
{"learn":[3.260128799],"iteration":851,"passed_time":1.9942502,"remaining_time":0.3464190489},
{"learn":[3.258972952],"iteration":852,"passed_time":1.995850099,"remaining_time":0.3439507205},
{"learn":[3.258724846],"iteration":853,"passed_time":1.998094213,"remaining_time":0.3415945609},
{"learn":[3.25686724],"iteration":854,"passed_time":1.999968947,"remaining_time":0.3391760202},
{"learn":[3.255750259],"iteration":855,"passed_time":2.001804427,"remaining_time":0.3367521465},
{"learn":[3.254915866],"iteration":856,"passed_time":2.003683887,"remaining_time":0.3343369846},
{"learn":[3.254348625],"iteration":857,"passed_time":2.005363084,"remaining_time":0.3318899276},
{"learn":[3.253408514],"iteration":858,"passed_time":2.007088283,"remaining_time":0.3294522094},
{"learn":[3.253291714],"iteration":859,"passed_time":2.008827162,"remaining_time":0.3270183753},
{"learn":[3.250186342],"iteration":860,"passed_time":2.010865996,"remaining_time":0.3246345802},
{"learn":[3.249141318],"iteration":861,"passed_time":2.012691561,"remaining_time":0.3222174425},
{"learn":[3.246300388],"iteration":862,"passed_time":2.014460992,"remaining_time":0.3197927647},
{"learn":[3.245205135],"iteration":863,"passed_time":2.016263564,"remaining_time":0.3173748202},
{"learn":[3.244403535],"iteration":864,"passed_time":2.017978217,"remaining_time":0.3149445772},
{"learn":[3.244211781],"iteration":865,"passed_time":2.019537525,"remaining_time":0.3124919497},
{"learn":[3.242286347],"iteration":866,"passed_time":2.021227092,"remaining_time":0.3100613648},
{"learn":[3.239606746],"iteration":867,"passed_time":2.023084172,"remaining_time":0.3076579616},
{"learn":[3.236773361],"iteration":868,"passed_time":2.024816931,"remaining_time":0.3052370748},
{"learn":[3.234552446],"iteration":869,"passed_time":2.026544168,"remaining_time":0.3028169446},
{"learn":[3.233724647],"iteration":870,"passed_time":2.028247864,"remaining_time":0.3003949189},
{"learn":[3.230851485],"iteration":871,"passed_time":2.029914088,"remaining_time":0.2979690404},
{"learn":[3.227728941],"iteration":872,"passed_time":2.031700954,"remaining_time":0.2955624527},
{"learn":[3.225787575],"iteration":873,"passed_time":2.033381511,"remaining_time":0.293141957},
{"learn":[3.222797487],"iteration":874,"passed_time":2.035032016,"remaining_time":0.2907188594},
{"learn":[3.22137014],"iteration":875,"passed_time":2.037309724,"remaining_time":0.2883863079},
{"learn":[3.219701963],"iteration":876,"passed_time":2.039888648,"remaining_time":0.2860961274},
{"learn":[3.21783327],"iteration":877,"passed_time":2.041949958,"remaining_time":0.2837333654},
{"learn":[3.217713355],"iteration":878,"passed_time":2.043849814,"remaining_time":0.2813490642},
{"learn":[3.217666091],"iteration":879,"passed_time":2.045634943,"remaining_time":0.2789502195},
{"learn":[3.214962005],"iteration":880,"passed_time":2.047369951,"remaining_time":0.2765459979},
{"learn":[3.214081828],"iteration":881,"passed_time":2.04911716,"remaining_time":0.2741449261},
{"learn":[3.213358337],"iteration":882,"passed_time":2.05089415,"remaining_time":0.2717492815},
{"learn":[3.210850401],"iteration":883,"passed_time":2.052666222,"remaining_time":0.2693543911},
{"learn":[3.207810328],"iteration":884,"passed_time":2.054701472,"remaining_time":0.2669951065},
{"learn":[3.204935073],"iteration":885,"passed_time":2.05644522,"remaining_time":0.2645990463},
{"learn":[3.20280198],"iteration":886,"passed_time":2.05823535,"remaining_time":0.2622103659},
{"learn":[3.200663495],"iteration":887,"passed_time":2.059993814,"remaining_time":0.2598190395},
{"learn":[3.197301669],"iteration":888,"passed_time":2.061768496,"remaining_time":0.2574311621},
{"learn":[3.195666943],"iteration":889,"passed_time":2.063469018,"remaining_time":0.2550354966},
{"learn":[3.193886506],"iteration":890,"passed_time":2.065231369,"remaining_time":0.2526489554},
{"learn":[3.190601248],"iteration":891,"passed_time":2.067597668,"remaining_time":0.2503369374},
{"learn":[3.188983797],"iteration":892,"passed_time":2.06938269,"remaining_time":0.2479551487},
{"learn":[3.187365749],"iteration":893,"passed_time":2.071170038,"remaining_time":0.2455749709},
{"learn":[3.186160771],"iteration":894,"passed_time":2.072922055,"remaining_time":0.2431919729},
{"learn":[3.185358981],"iteration":895,"passed_time":2.074909675,"remaining_time":0.2408377301},
{"learn":[3.183832164],"iteration":896,"passed_time":2.077062083,"remaining_time":0.2385032269},
{"learn":[3.183106966],"iteration":897,"passed_time":2.079030186,"remaining_time":0.2361481948},
{"learn":[3.182838152],"iteration":898,"passed_time":2.080882351,"remaining_time":0.2337809982},
{"learn":[3.180835453],"iteration":899,"passed_time":2.083360266,"remaining_time":0.231484474},
{"learn":[3.179957348],"iteration":900,"passed_time":2.085326334,"remaining_time":0.2291313064},
{"learn":[3.179752966],"iteration":901,"passed_time":2.087175284,"remaining_time":0.2267662726},
{"learn":[3.178851983],"iteration":902,"passed_time":2.088914915,"remaining_time":0.2243906387},
{"learn":[3.176748586],"iteration":903,"passed_time":2.090783137,"remaining_time":0.2220300677},
{"learn":[3.172960988],"iteration":904,"passed_time":2.092516671,"remaining_time":0.2196564462},
{"learn":[3.172794225],"iteration":905,"passed_time":2.09423711,"remaining_time":0.217282879},
{"learn":[3.169996507],"iteration":906,"passed_time":2.096038086,"remaining_time":0.2149190099},
{"learn":[3.16813015],"iteration":907,"passed_time":2.097839003,"remaining_time":0.2125563748},
{"learn":[3.166920871],"iteration":908,"passed_time":2.099650007,"remaining_time":0.2101959853},
{"learn":[3.16531606],"iteration":909,"passed_time":2.101493164,"remaining_time":0.2078399832},
{"learn":[3.162035247],"iteration":910,"passed_time":2.103319581,"remaining_time":0.2054834717},
{"learn":[3.16189467],"iteration":911,"passed_time":2.104987418,"remaining_time":0.2031128211},
{"learn":[3.161008416],"iteration":912,"passed_time":2.106779874,"remaining_time":0.2007555849},
{"learn":[3.160560787],"iteration":913,"passed_time":2.108456554,"remaining_time":0.1983886911},
{"learn":[3.160416261],"iteration":914,"passed_time":2.110180646,"remaining_time":0.1960277103},
{"learn":[3.15844291],"iteration":915,"passed_time":2.112076879,"remaining_time":0.1936839059},
{"learn":[3.155040501],"iteration":916,"passed_time":2.113877904,"remaining_time":0.1913324603},
{"learn":[3.154937548],"iteration":917,"passed_time":2.115652964,"remaining_time":0.1889798944},
{"learn":[3.153721161],"iteration":918,"passed_time":2.117553475,"remaining_time":0.1866396426},
{"learn":[3.153170511],"iteration":919,"passed_time":2.119364204,"remaining_time":0.1842925395},
{"learn":[3.153113601],"iteration":920,"passed_time":2.121080293,"remaining_time":0.1819384833},
{"learn":[3.150607379],"iteration":921,"passed_time":2.123182847,"remaining_time":0.1796185055},
{"learn":[3.148408359],"iteration":922,"passed_time":2.125002963,"remaining_time":0.1772754368},
{"learn":[3.147495728],"iteration":923,"passed_time":2.126797721,"remaining_time":0.1749314143},
{"learn":[3.146946235],"iteration":924,"passed_time":2.128600484,"remaining_time":0.1725892284},
{"learn":[3.14472738],"iteration":925,"passed_time":2.130418251,"remaining_time":0.1702494067},
{"learn":[3.144469477],"iteration":926,"passed_time":2.132258236,"remaining_time":0.1679124609},
{"learn":[3.142975516],"iteration":927,"passed_time":2.133924908,"remaining_time":0.1655631394},
{"learn":[3.14079113],"iteration":928,"passed_time":2.135886034,"remaining_time":0.1632377916},
{"learn":[3.138173032],"iteration":929,"passed_time":2.137808458,"remaining_time":0.1609103141},
{"learn":[3.136352813],"iteration":930,"passed_time":2.139672822,"remaining_time":0.1585794035},
{"learn":[3.133735004],"iteration":931,"passed_time":2.141481926,"remaining_time":0.1562454624},
{"learn":[3.1319496],"iteration":932,"passed_time":2.143250063,"remaining_time":0.1539097044},
{"learn":[3.129865343],"iteration":933,"passed_time":2.145216045,"remaining_time":0.1515891423},
{"learn":[3.129830206],"iteration":934,"passed_time":2.14651008,"remaining_time":0.1492226259},
{"learn":[3.126676562],"iteration":935,"passed_time":2.148266605,"remaining_time":0.1468900242},
{"learn":[3.12645665],"iteration":936,"passed_time":2.149844307,"remaining_time":0.144546629},
{"learn":[3.126378007],"iteration":937,"passed_time":2.151679515,"remaining_time":0.1422218869},
{"learn":[3.124621914],"iteration":938,"passed_time":2.15348471,"remaining_time":0.1398962378},
{"learn":[3.123379018],"iteration":939,"passed_time":2.155278878,"remaining_time":0.1375709922},
{"learn":[3.123332451],"iteration":940,"passed_time":2.156931304,"remaining_time":0.1352379883},
{"learn":[3.122432444],"iteration":941,"passed_time":2.158814317,"remaining_time":0.1329206267},
{"learn":[3.121889006],"iteration":942,"passed_time":2.160640649,"remaining_time":0.1306007603},
{"learn":[3.121070914],"iteration":943,"passed_time":2.162460765,"remaining_time":0.1282815708},
{"learn":[3.118444705],"iteration":944,"passed_time":2.164407018,"remaining_time":0.1259707788},
{"learn":[3.116820458],"iteration":945,"passed_time":2.16617602,"remaining_time":0.1236506396},
{"learn":[3.114971041],"iteration":946,"passed_time":2.167825403,"remaining_time":0.1213249697},
{"learn":[3.114685138],"iteration":947,"passed_time":2.169734825,"remaining_time":0.1190149904},
{"learn":[3.113399363],"iteration":948,"passed_time":2.171628798,"remaining_time":0.116705025},
{"learn":[3.110575399],"iteration":949,"passed_time":2.173355208,"remaining_time":0.1143871162},
{"learn":[3.110466553],"iteration":950,"passed_time":2.175169953,"remaining_time":0.1120750028},
{"learn":[3.108691641],"iteration":951,"passed_time":2.176950503,"remaining_time":0.1097622102},
{"learn":[3.107898017],"iteration":952,"passed_time":2.178834444,"remaining_time":0.1074556336},
{"learn":[3.105551729],"iteration":953,"passed_time":2.180704341,"remaining_time":0.1051492659},
{"learn":[3.104824945],"iteration":954,"passed_time":2.182478793,"remaining_time":0.1028393148},
{"learn":[3.103186704],"iteration":955,"passed_time":2.184244612,"remaining_time":0.1005300868},
{"learn":[3.102330655],"iteration":956,"passed_time":2.185986201,"remaining_time":0.09822090559},
{"learn":[3.102291298],"iteration":957,"passed_time":2.18763484,"remaining_time":0.09590883434},
{"learn":[3.100363529],"iteration":958,"passed_time":2.189422112,"remaining_time":0.09360407362},
{"learn":[3.097871596],"iteration":959,"passed_time":2.191246751,"remaining_time":0.09130194795},
{"learn":[3.097372213],"iteration":960,"passed_time":2.1931225,"remaining_time":0.08900289023},
{"learn":[3.095981813],"iteration":961,"passed_time":2.194957628,"remaining_time":0.08670310795},
{"learn":[3.095347452],"iteration":962,"passed_time":2.196775126,"remaining_time":0.08440361335},
{"learn":[3.094728409],"iteration":963,"passed_time":2.198551676,"remaining_time":0.08210358955},
{"learn":[3.094118537],"iteration":964,"passed_time":2.200482212,"remaining_time":0.07981023568},
{"learn":[3.093793695],"iteration":965,"passed_time":2.202277079,"remaining_time":0.07751285784},
{"learn":[3.092581602],"iteration":966,"passed_time":2.204074984,"remaining_time":0.07521662303},
{"learn":[3.091694202],"iteration":967,"passed_time":2.205841628,"remaining_time":0.07292038441},
{"learn":[3.090298312],"iteration":968,"passed_time":2.20764823,"remaining_time":0.07062651717},
{"learn":[3.090020107],"iteration":969,"passed_time":2.209312011,"remaining_time":0.06832923745},
{"learn":[3.088949869],"iteration":970,"passed_time":2.211034471,"remaining_time":0.06603501511},
{"learn":[3.086700204],"iteration":971,"passed_time":2.212826855,"remaining_time":0.06374398347},
{"learn":[3.086584317],"iteration":972,"passed_time":2.214501455,"remaining_time":0.06145070842},
{"learn":[3.084850742],"iteration":973,"passed_time":2.216255181,"remaining_time":0.05916081592},
{"learn":[3.084239948],"iteration":974,"passed_time":2.218043784,"remaining_time":0.05687291754},
{"learn":[3.082561673],"iteration":975,"passed_time":2.219951199,"remaining_time":0.0545889639},
{"learn":[3.07991814],"iteration":976,"passed_time":2.221644913,"remaining_time":0.05230075027},
{"learn":[3.079350277],"iteration":977,"passed_time":2.223320685,"remaining_time":0.05001334874},
{"learn":[3.077637462],"iteration":978,"passed_time":2.225275848,"remaining_time":0.04773318979},
{"learn":[3.076733301],"iteration":979,"passed_time":2.22699144,"remaining_time":0.04544880489},
{"learn":[3.07594065],"iteration":980,"passed_time":2.228771421,"remaining_time":0.04316682671},
{"learn":[3.072594655],"iteration":981,"passed_time":2.23061455,"remaining_time":0.04088702842},
{"learn":[3.071977674],"iteration":982,"passed_time":2.232546612,"remaining_time":0.03860965657},
{"learn":[3.069532634],"iteration":983,"passed_time":2.234493497,"remaining_time":0.0363332276},
{"learn":[3.068870784],"iteration":984,"passed_time":2.23629636,"remaining_time":0.03405527452},
{"learn":[3.068801463],"iteration":985,"passed_time":2.237990877,"remaining_time":0.03177674674},
{"learn":[3.067433249],"iteration":986,"passed_time":2.239764439,"remaining_time":0.02950044347},
{"learn":[3.065611456],"iteration":987,"passed_time":2.241507757,"remaining_time":0.02722479057},
{"learn":[3.063039162],"iteration":988,"passed_time":2.243301796,"remaining_time":0.02495077832},
{"learn":[3.06177873],"iteration":989,"passed_time":2.245218079,"remaining_time":0.02267897049},
{"learn":[3.061689148],"iteration":990,"passed_time":2.246937506,"remaining_time":0.02040609239},
{"learn":[3.058984039],"iteration":991,"passed_time":2.248936241,"remaining_time":0.01813658259},
{"learn":[3.057492984],"iteration":992,"passed_time":2.250742453,"remaining_time":0.015866261},
{"learn":[3.057290731],"iteration":993,"passed_time":2.252542023,"remaining_time":0.01359683314},
{"learn":[3.056068348],"iteration":994,"passed_time":2.254228651,"remaining_time":0.01132778217},
{"learn":[3.054987307],"iteration":995,"passed_time":2.2560443,"remaining_time":0.009060418876},
{"learn":[3.054200234],"iteration":996,"passed_time":2.257915202,"remaining_time":0.006794127988},
{"learn":[3.052732869],"iteration":997,"passed_time":2.259752467,"remaining_time":0.004528562058},
{"learn":[3.051787862],"iteration":998,"passed_time":2.261565502,"remaining_time":0.002263829331},
{"learn":[3.051366222],"iteration":999,"passed_time":2.264484301,"remaining_time":0}
]}